<?xml version="1.0" ?><text author="Twain, Mark" dateCollected="2019-10-22" id="autogum_fiction_doc388" shortTile="horsestale" sourceURL="http://gutenberg.readingroo.ms/1/0/8/1086/1086-0.txt" title="A Horse's Tale" type="fiction">
<head>
<s type="frag">
Contents	NNS	content
</s>
</head>
<p>
<s type="frag">
CHAP	NNP	CHAP
.	.	.
</s>
<s type="frag">
PAGE	NNP	PAGE
I.	NNP	I.
SOLDIER	NNP	Soldier
BOY	NNP	BOY
—	:	—
PRIVATELY	NNP	PrI-AteLy
TO	TO	TO
HIMSELF	NNP	HIMSELF
1	CD	1
II	NNP	II
.	.	.
</s>
<s type="frag">
LETTER	NN	LETTER
FROM	IN	FROM
ROUEN	NNP	Rouen
—	:	—
TO	TO	TO
GENERAL	NNP	GENERAL
ALISON	NNP	ALISON
12	CD	@card@
III	NNP	III
.	.	.
</s>
<s type="frag">
GENERAL	NNP	GENERAL
ALISON	NNP	ALISON
TO	TO	TO
HIS	PRP$	his
MOTHER	NNP	MOTHER
19	CD	@card@
IV	NNP	IV
.	.	.
</s>
<s type="frag">
CATHY	NNP	CathY
TO	TO	TO
HER	PRP$	HER
AUNT	NNP	AUNT
MERCEDES	NNP	MER8EDES
25	CD	@card@
V.	NNP	V.
GENERAL	NNP	GENERAL
ALISON	NNP	ALISON
TO	TO	TO
MERCEDES	NNP	MER8EDES
33	CD	@card@
VI	NNP	VI
.	.	.
</s>
<s type="frag">
SOLDIER	NNP	Soldier
BOY	NNP	BOY
AND	CC	and
THE	DT	the
MEXICAN	NNP	MEXICAN
PLUG	NNP	PLUG
56	CD	@card@
VII	NNP	VII
.	.	.
</s>
<s type="frag">
SOLDIER	NNP	Soldier
BOY	NNP	BOY
AND	CC	and
SHEKELS	NNP	SHEKelS
82	CD	@card@
VIII	NNP	VIII
.	.	.
</s>
<s type="frag">
THE	DT	the
SCOUT-START	NNP	SCOUT-START
.	.	.
</s>
<s type="frag">
BB	NNP	BB
AND	CC	and
LIEUTENANT-GENERAL	NNP	LIEUTENANT-GENERAL
88	CD	@card@
ALISON	NNP	ALISON
IX	NNP	IX
.	.	.
</s>
<s type="frag">
SOLDIER	NNP	Soldier
BOY	NNP	BOY
AND	CC	and
SHEKELS	NNP	SHEKelS
AGAIN	RB	AGAIN
90	CD	@card@
X.	FW	X.
GENERAL	NNP	GENERAL
ALISON	NNP	ALISON
AND	CC	and
DORCAS	NNP	DORCAS
100	CD	@card@
XI	NNP	XI
.	.	.
</s>
<s type="frag">
SEVERAL	JJ	SEVERAL
MONTHS	NNS	MONTHS
LATER	RBR	later
.	.	.
</s>
<s type="frag">
ANTONIO	NNP	ANTONIO
AND	CC	and
THORNDIKE	NNP	THORNDIKE
116	CD	@card@
XII	NNP	XII
.	.	.
</s>
<s type="frag">
MONGREL	NNP	MongreL
AND	CC	and
THE	DT	the
OTHER	NNP	OTHER
HORSE	NNP	HORSE
129	CD	@card@
XIII	NNP	XIII
.	.	.
</s>
<s type="frag">
GENERAL	NNP	GENERAL
ALISON	NNP	ALISON
TO	TO	TO
HIS	PRP$	his
MOTHER	NNP	MOTHER
133	CD	@card@
XIV	NNP	XIV
.	.	.
</s>
<s type="frag">
SOLDIER	NNP	Soldier
BOY	NNP	BOY
—	:	—
TO	TO	TO
HIMSELF	NNP	HIMSELF
145	CD	@card@
XV	NNP	XV
.	.	.
</s>
<s type="frag">
GENERAL	NNP	GENERAL
ALISON	NNP	ALISON
TO	TO	TO
MRS	NNP	MRS
.	.	.
</s>
<s type="frag">
DRAKE	NNP	Drake
,	,	,
THE	DT	the
COLONEL’S	NNP	ColoneLS
WIFE	NNP	wife
149	CD	@card@
</s>
</p>
<head>
<s type="frag">
Illustrations	NNS	Illustrations
</s>
</head>
<p>
<s type="decl">
“	``	"
Buffalo	NNP	Buffalo
Bill	NNP	Bill
took	VBD	take
me	PRP	me
on	IN	on
Soldier	NNP	Soldier
Boy	NNP	boy
to	TO	to
<hi rend="italic">
Frontispiece	NNP	frontispiece
</hi>
Thunder-Bird	NNP	Thunder-Bird
’s	POS	's
Camp	NNP	Camp
”	''	"
</s>
<s type="decl">
“	``	"
Look	VB	look
at	IN	at
that	DT	that
file	NN	file
of	IN	of
cats	NNS	cat
in	IN	in
your	PRP$	your
chair	NN	chair
”	''	"
p.	,	P.
48	CD	@card@
“	''	"
Every	DT	every
morning	NN	morning
they	PRP	they
go	VBP	go
clattering	VBG	clatter
down	RP	down
into	IN	into
the	DT	the
66	CD	@card@
plain	NN	plain
”	''	"
</s>
<s type="decl">
“	``	"
There	EX	There
was	VBD	be
nothing	NN	nothing
to	TO	to
do	VB	do
but	CC	but
stand	VB	stand
by	IN	by
”	``	"
92	CD	@card@
“	``	"
His	PRP$	his
strength	NN	strength
failed	VBD	fail
and	CC	and
he	PRP	he
fell	VBD	fall
at	IN	at
her	PRP$	her
feet	NNS	foot
”	''	"
150	CD	@card@
</s>
</p>
<head>
<s type="frag">
Acknowledgements	NNS	Acknowledgements
</s>
</head>
<p>
<s type="decl">
Although	IN	although
I	PRP	I
have	VBP	have
had	VBN	have
several	JJ	several
opportunities	NNS	opportunity
to	TO	to
see	VB	see
a	DT	a
bull-fight	NN	bull-fight
,	,	,
I	PRP	I
have	VBP	have
never	RB	never
seen	VBN	see
one	CD	one
;	:	;
but	CC	but
I	PRP	I
needed	VBD	need
a	DT	a
bull-fight	NN	bull-fight
in	IN	in
this	DT	this
book	NN	book
,	,	,
and	CC	and
a	DT	a
trustworthy	JJ	trustworthy
one	PRP	one
will	MD	will
be	VB	be
found	VBN	find
in	IN	in
it	PRP	it
.	.	.
</s>
<s type="decl">
I	PRP	I
got	VBD	get
it	PRP	it
out	IN	out
of	IN	of
John	NNP	John
Hay	NNP	hay
’s	POS	's
<hi rend="italic">
Castilian	NNP	Castilian
Days	NNPS	Days
</hi>
,	,	,
reducing	VBG	reduce
and	CC	and
condensing	VBG	condense
it	PRP	it
to	TO	to
fit	VB	fit
the	DT	the
requirements	NNS	requirement
of	IN	of
this	DT	this
small	JJ	small
story	NN	story
.	.	.
</s>
<s type="sub">
Mr.	NNP	Mr.
Hay	NNP	hay
and	CC	and
I	PRP	I
were	VBD	be
friends	NNS	friend
from	IN	from
early	JJ	early
times	NNS	time
,	,	,
and	CC	and
if	IN	if
he	PRP	he
were	VBD	be
still	RB	still
with	IN	with
us	PRP	us
he	PRP	he
would	MD	would
not	RB	not
rebuke	VB	rebuke
me	PRP	me
for	IN	for
the	DT	the
liberty	NN	liberty
I	PRP	I
have	VBP	have
taken	VBN	take
.	.	.
</s>
</p>
<p>
<s type="decl">
The	DT	the
knowledge	NN	knowledge
of	IN	of
military	JJ	military
minutiæ	NN	minutiæ
exhibited	VBN	exhibit
in	IN	in
this	DT	this
book	NN	book
will	MD	will
be	VB	be
found	VBN	find
to	TO	to
be	VB	be
correct	JJ	correct
,	,	,
but	CC	but
it	PRP	it
is	VBZ	be
not	RB	not
mine	JJ	mine
;	:	;
I	PRP	I
took	VBD	take
it	PRP	it
from	IN	from
<hi rend="italic">
Army	NNP	Army
Regulations	NNPS	regulation
</hi>
,	,	,
ed	NN	ed
.	.	.
1904	CD	@card@
;	:	;
<hi rend="italic">
Hardy	NNP	Hardy
’s	POS	's
Tactics	NNPS	tactic
</hi>
—	:	—
<hi rend="italic">
Cavalry	NNP	Cavalry
</hi>
,	,	,
revised	VBN	revise
ed	NN	ed
.	.	.
,	,	,
1861	CD	@card@
;	:	;
and	CC	and
<hi rend="italic">
Jomini	NNP	Jomini
’s	POS	's
Handbook	NNP	Handbook
of	IN	of
Military	NNP	Military
Etiquette	NNP	Etiquette
</hi>
,	,	,
West	NNP	West
Point	NNP	Point
ed	NNP	ed
.	.	.
,	,	,
1905	CD	@card@
.	.	.
</s>
</p>
<p>
<s type="decl">
It	PRP	it
would	MD	would
not	RB	not
be	VB	be
honest	JJ	hone
in	IN	in
me	PRP	me
to	TO	to
encourage	VB	encourage
by	IN	by
silence	NN	silence
the	DT	the
inference	NN	inference
that	WDT	that
I	PRP	I
composed	VBD	compose
the	DT	the
Horse	NNP	Horse
’s	POS	's
private	JJ	private
bugle-call	NN	bugle-call
,	,	,
for	IN	for
I	PRP	I
did	VBD	do
not	RB	not
.	.	.
</s>
<s type="decl">
I	PRP	I
lifted	VBD	lift
it	PRP	it
,	,	,
as	IN	as
Aristotle	NNP	Aristotle
says	VBZ	say
.	.	.
</s>
<s type="decl">
It	PRP	it
is	VBZ	be
the	DT	the
opening	NN	opening
strain	NN	strain
in	IN	in
<hi rend="italic">
The	DT	the
Pizzicato	NNP	Pizzicato
</hi>
in	IN	in
<hi rend="italic">
Sylvia	NNP	Sylvia
</hi>
,	,	,
by	IN	by
Delibes	NNP	Delibes
.	.	.
</s>
<s type="decl">
When	WRB	when
that	DT	that
master	NN	master
was	VBD	be
composing	VBG	compose
it	PRP	it
he	PRP	he
did	VBD	do
not	RB	not
know	VB	know
it	PRP	it
was	VBD	be
a	DT	a
bugle-call	NN	bugle-call
,	,	,
it	PRP	it
was	VBD	be
I	PRP	I
that	WDT	that
found	VBD	find
it	PRP	it
out	RP	out
.	.	.
</s>
</p>
<p>
<s type="decl">
Along	RB	along
through	IN	through
the	DT	the
book	NN	book
I	PRP	I
have	VBP	have
distributed	VBN	distribute
a	DT	a
few	JJ	few
anachronisms	NNS	anachronis
and	CC	and
unborn	JJ	unborn
historical	JJ	historical
incidents	NNS	incident
and	CC	and
such	JJ	such
things	NNS	thing
,	,	,
so	RB	so
as	IN	as
to	TO	to
help	VB	help
the	DT	the
tale	NN	tale
over	IN	over
the	DT	the
difficult	JJ	difficult
places	NNS	place
.	.	.
</s>
<s type="decl">
This	DT	this
idea	NN	idea
is	VBZ	be
not	RB	not
original	JJ	original
with	IN	with
me	PRP	me
;	:	;
</s>
<s type="decl">
I	PRP	I
got	VBD	get
it	PRP	it
out	IN	out
of	IN	of
Herodotus	NNP	Herodotus
.	.	.
</s>
<s type="decl">
Herodotus	NNP	Herodotus
says	VBZ	say
,	,	,
</s>
<s type="decl">
“	``	"
Very	RB	very
few	JJ	few
things	NNS	thing
happen	VBP	happen
at	IN	at
the	DT	the
right	JJ	right
time	NN	time
,	,	,
and	CC	and
the	DT	the
rest	NN	rest
do	VBP	do
not	RB	not
happen	VB	happen
at	IN	at
all	DT	all
:	:	:
the	DT	the
conscientious	JJ	conscientious
historian	NN	historian
will	MD	will
correct	VB	correct
these	DT	these
defects	NNS	defect
.	.	.
”	''	"
</s>
</p>
<p>
<s type="decl">
The	DT	the
cats	NNS	cat
in	IN	in
the	DT	the
chair	NN	chair
do	VBP	do
not	RB	not
belong	VB	belong
to	TO	to
me	PRP	me
,	,	,
but	CC	but
to	TO	to
another	DT	another
.	.	.
</s>
</p>
<p>
<s type="decl">
These	DT	these
are	VBP	be
all	PDT	all
the	DT	the
exceptions	NNS	exception
.	.	.
</s>
<s type="decl">
What	WP	What
is	VBZ	be
left	VBN	leave
of	IN	of
the	DT	the
book	NN	book
is	VBZ	be
mine	NN	mine
.	.	.
</s>
</p>
<p>
<s type="frag">
MARK	NNP	MARK
TWAIN	NNP	TWAIN
.	.	.
</s>
</p>
<p>
<s type="frag">
LONE	NNP	LONE
TREE	NNP	Tree
HILL	NNP	HILL
,	,	,
DUBLIN	NNP	DUDLIN
,	,	,
NEW	NNP	NEW
HAMPSHIRE	NNP	HAMPSHIRE
,	,	,
<hi rend="italic">
October	NNP	October
</hi>
,	,	,
1905	CD	@card@
.	.	.
</s>
</p>
<head>
<s type="frag">
Part	NN	part
I	CD	I
</s>
</head>
<p>
<s type="decl">
I	PRP	I
SOLDIER	NNP	Soldier
BOY	NNP	BOY
—	:	—
PRIVATELY	NNP	PrI-AteLy
TO	TO	TO
HIMSELF	NNP	HIMSELF
</s>
</p>
<p>
<s type="decl">
I	PRP	I
AM	VBP	AM
Buffalo	NNP	Buffalo
Bill	NNP	Bill
’s	POS	's
horse	NN	horse
.	.	.
</s>
<s type="decl">
I	PRP	I
have	VBP	have
spent	VBN	spend
my	PRP$	my
life	NN	life
under	IN	under
his	PRP$	his
saddle	NN	saddle
—	:	—
with	IN	with
him	PRP	him
in	IN	in
it	PRP	it
,	,	,
too	RB	too
,	,	,
and	CC	and
he	PRP	he
is	VBZ	be
good	JJ	good
for	IN	for
two	CD	two
hundred	CD	hundred
pounds	NNS	pound
,	,	,
without	IN	without
his	PRP$	his
clothes	NNS	clothes
;	:	;
and	CC	and
there	EX	there
is	VBZ	be
no	DT	no
telling	VBG	tell
how	WRB	how
much	JJ	much
he	PRP	he
does	VBZ	do
weigh	VB	weigh
when	WRB	when
he	PRP	he
is	VBZ	be
out	RP	out
on	IN	on
the	DT	the
war-path	NN	war-path
and	CC	and
has	VBZ	have
his	PRP$	his
batteries	NNS	battery
belted	VBN	belt
on	RP	on
.	.	.
</s>
<s type="decl">
He	PRP	he
is	VBZ	be
over	IN	over
six	CD	six
feet	NNS	foot
,	,	,
is	VBZ	be
young	JJ	young
,	,	,
has	VBZ	have
n’t	RB	n't
an	DT	an
ounce	NN	ounce
of	IN	of
waste	NN	waste
flesh	NN	flesh
,	,	,
is	VBZ	be
straight	JJ	straight
,	,	,
graceful	JJ	graceful
,	,	,
springy	VBG	springy
in	IN	in
his	PRP$	his
motions	NNS	motion
,	,	,
quick	JJ	quick
as	IN	as
a	DT	a
cat	NN	cat
,	,	,
and	CC	and
has	VBZ	have
a	DT	a
handsome	JJ	handsome
face	NN	face
,	,	,
and	CC	and
black	JJ	black
hair	NN	hair
dangling	VBG	dangle
down	RP	down
on	IN	on
his	PRP$	his
shoulders	NNS	shoulder
,	,	,
and	CC	and
is	VBZ	be
beautiful	JJ	beautiful
to	TO	to
look	VB	look
at	IN	at
;	:	;
and	CC	and
nobody	NN	nobody
is	VBZ	be
braver	JJR	brave
than	IN	than
he	PRP	he
is	VBZ	be
,	,	,
and	CC	and
nobody	NN	nobody
is	VBZ	be
stronger	JJR	strong
,	,	,
except	IN	except
myself	PRP	myself
.	.	.
</s>
<s type="decl">
Yes	UH	yes
,	,	,
a	DT	a
person	NN	person
that	WDT	that
doubts	VBZ	doubt
that	IN	that
he	PRP	he
is	VBZ	be
fine	JJ	fine
to	TO	to
see	VB	see
should	MD	should
see	VB	see
him	PRP	him
in	IN	in
his	PRP$	his
beaded	JJ	bead
buck-skins	NN	buck-skins
,	,	,
on	IN	on
my	PRP$	my
back	NN	back
and	CC	and
his	PRP$	his
rifle	NN	rifle
peeping	VBG	peeping
above	IN	above
his	PRP$	his
shoulder	NN	shoulder
,	,	,
chasing	VBG	chase
a	DT	a
hostile	JJ	hostile
trail	NN	trail
,	,	,
with	IN	with
me	PRP	me
going	VBG	go
like	IN	like
the	DT	the
wind	NN	wind
and	CC	and
his	PRP$	his
hair	NN	hair
streaming	VBG	stream
out	RP	out
behind	IN	behind
from	IN	from
the	DT	the
shelter	NN	shelter
of	IN	of
his	PRP$	his
broad	JJ	broad
slouch	NN	slouch
.	.	.
</s>
<s type="decl">
Yes	UH	yes
,	,	,
he	PRP	he
is	VBZ	be
a	DT	a
sight	NN	sight
to	TO	to
look	VB	look
at	IN	at
then	RB	then
—	:	—
and	CC	and
I	PRP	I
’m	VBP	be
part	NN	part
of	IN	of
it	PRP	it
myself	PRP	myself
.	.	.
</s>
</p>
<p>
<s type="decl">
I	PRP	I
am	VBP	be
his	PRP$	his
favorite	JJ	favorite
horse	NN	horse
,	,	,
out	IN	out
of	IN	of
dozens	NNS	dozen
.	.	.
</s>
<s type="decl">
Big	JJ	Big
as	IN	as
he	PRP	he
is	VBZ	be
,	,	,
I	PRP	I
have	VBP	have
carried	VBN	carry
him	PRP	him
eighty-one	JJ	eighty-one
miles	NNS	mile
between	IN	between
nightfall	NN	nightfall
and	CC	and
sunrise	NN	sunrise
on	IN	on
the	DT	the
scout	NN	scout
;	:	;
and	CC	and
I	PRP	I
am	VBP	be
good	JJ	good
for	IN	for
fifty	CD	fifty
,	,	,
day	NN	day
in	IN	in
and	CC	and
day	NN	day
out	RP	out
,	,	,
and	CC	and
all	PDT	all
the	DT	the
time	NN	time
.	.	.
</s>
<s type="decl">
I	PRP	I
am	VBP	be
not	RB	not
large	JJ	large
,	,	,
but	CC	but
I	PRP	I
am	VBP	be
built	VBN	build
on	IN	on
a	DT	a
business	NN	business
basis	NN	basis
.	.	.
</s>
<s type="decl">
I	PRP	I
have	VBP	have
carried	VBN	carry
him	PRP	him
thousands	NNS	thousand
and	CC	and
thousands	NNS	thousand
of	IN	of
miles	NNS	mile
on	IN	on
scout	NN	scout
duty	NN	duty
for	IN	for
the	DT	the
army	NN	army
,	,	,
and	CC	and
there	EX	there
’s	VBZ	be
not	RB	not
a	DT	a
gorge	NN	gorge
,	,	,
nor	CC	nor
a	DT	a
pass	NN	pass
,	,	,
nor	CC	nor
a	DT	a
valley	NN	valley
,	,	,
nor	CC	nor
a	DT	a
fort	NNP	fort
,	,	,
nor	IN	nor
a	DT	a
trading	NN	trading
post	NN	post
,	,	,
nor	CC	nor
a	DT	a
buffalo-range	NN	buffalo-range
in	IN	in
the	DT	the
whole	JJ	whole
sweep	NN	sweep
of	IN	of
the	DT	the
Rocky	NNP	Rocky
Mountains	NNPS	Mountain
and	CC	and
the	DT	the
Great	NNP	Great
Plains	NNPS	Plains
that	WDT	that
we	PRP	we
do	VBP	do
n’t	RB	n't
know	VB	know
as	RB	as
well	RB	well
as	IN	as
we	PRP	we
know	VBP	know
the	DT	the
bugle-calls	NNS	bugle-calls
.	.	.
</s>
<s type="decl">
He	PRP	he
is	VBZ	be
Chief	NNP	Chief
of	IN	of
Scouts	NNPS	scout
to	TO	to
the	DT	the
Army	NNP	Army
of	IN	of
the	DT	the
Frontier	NNP	Frontier
,	,	,
and	CC	and
it	PRP	it
makes	VBZ	make
us	PRP	us
very	RB	very
important	JJ	important
.	.	.
</s>
<s type="decl">
In	IN	in
such	PDT	such
a	DT	a
position	NN	position
as	IN	as
I	PRP	I
hold	VBP	hold
in	IN	in
the	DT	the
military	JJ	military
service	NN	service
one	CD	one
needs	VBZ	need
to	TO	to
be	VB	be
of	IN	of
good	JJ	good
family	NN	family
and	CC	and
possess	VBP	possess
an	DT	an
education	NN	education
much	RB	much
above	IN	above
the	DT	the
common	JJ	common
to	TO	to
be	VB	be
worthy	JJ	worthy
of	IN	of
the	DT	the
place	NN	place
.	.	.
</s>
<s type="decl">
I	PRP	I
am	VBP	be
the	DT	the
best-educated	JJ	best-educated
horse	NN	horse
outside	IN	outside
of	IN	of
the	DT	the
hippodrome	NN	hippodrome
,	,	,
everybody	NN	everybody
says	VBZ	say
,	,	,
and	CC	and
the	DT	the
best-mannered	JJ	best-mannered
.	.	.
</s>
<s type="decl">
It	PRP	it
may	MD	may
be	VB	be
so	RB	so
,	,	,
it	PRP	it
is	VBZ	be
not	RB	not
for	IN	for
me	PRP	me
to	TO	to
say	VB	say
;	:	;
modesty	NN	modesty
is	VBZ	be
the	DT	the
best	JJS	good
policy	NN	policy
,	,	,
I	PRP	I
think	VBP	think
.	.	.
</s>
<s type="decl">
Buffalo	NNP	Buffalo
Bill	NNP	Bill
taught	VBD	teach
me	PRP	me
the	DT	the
most	JJS	most
of	IN	of
what	WP	what
I	PRP	I
know	VBP	know
,	,	,
my	PRP$	my
mother	NN	mother
taught	VBD	teach
me	PRP	me
much	RB	much
,	,	,
and	CC	and
I	PRP	I
taught	VBD	teach
myself	PRP	myself
the	DT	the
rest	NN	rest
.	.	.
</s>
<s type="imp">
Lay	VB	lay
a	DT	a
row	NN	row
of	IN	of
moccasins	NNS	moccasin
before	IN	before
me	PRP	me
—	:	—
Pawnee	NNP	Pawnee
,	,	,
Sioux	NNP	sioux
,	,	,
Shoshone	NNP	Shoshone
,	,	,
Cheyenne	NNP	Cheyenne
,	,	,
Blackfoot	NNP	blackfoot
,	,	,
and	CC	and
as	IN	as
many	JJ	many
other	JJ	other
tribes	NNS	tribe
as	IN	as
you	PRP	you
please	VBP	please
—	:	—
and	CC	and
I	PRP	I
can	MD	can
name	VB	name
the	DT	the
tribe	NN	tribe
every	DT	every
moccasin	NN	moccasin
belongs	VBZ	belong
to	TO	to
by	IN	by
the	DT	the
make	NN	make
of	IN	of
it	PRP	it
.	.	.
</s>
<s type="imp">
Name	VB	name
it	PRP	it
in	IN	in
horse-talk	NN	horse-talk
,	,	,
and	CC	and
could	MD	could
do	VB	do
it	PRP	it
in	IN	in
American	NNP	American
if	IN	if
I	PRP	I
had	VBD	have
speech	NN	speech
.	.	.
</s>
</p>
</text>