<?xml version='1.0' encoding='utf8'?>
<text id="AMALGUM_voyage_washington" title="Washington Dulles International Airport" shortTitle="washington" author="Wikivoyage community (see URL)" type="voyage" dateCollected="2019-11-01" sourceURL="https://en.wikivoyage.org/wiki?curid=124041" speakerList="none" speakerCount="0">
<head>
<s type="frag">
Washington	NNP	Washington
Dulles	NNP	Dulles
International	NNP	International
Airport	NNP	Airport
</s>
</head>
<p>
<s type="decl">
<hi rend="bold">
<ref target="http://flydulles.com/">
Washington	NNP	Washington
Dulles	NNP	Dulles
International	NNP	International
Airport	NNP	Airport
</ref>
</hi>
(	-LRB-	(
IAD	NNP	IAD
)	-RRB-	)
is	VBZ	be
the	DT	the
main	JJ	main
international	JJ	international
airport	NN	airport
of	IN	of
the	DT	the
<ref target="Washington%2C%20D.C.">
Washington	NNP	Washington
,	,	,
D.C.	NNP	D.C.
</ref>
area	NN	area
and	CC	and
surrounding	VBG	surround
communities	NNS	community
.	.	.
</s>
</p>
<head>
<s type="imp">
Understand	VB	understand
</s>
</head>
<p>
<s type="decl">
Dulles	NNP	Dulles
is	VBZ	be
26	CD	26
miles	NNS	mile
west	RB	west
of	IN	of
DC	NNP	DC
in	IN	in
<ref target="Sterling%20%28Virginia%29">
Sterling	NNP	Sterling
</ref>
,	,	,
<ref target="Virginia">
Virginia	NNP	Virginia
</ref>
.	.	.
</s>
<s type="decl">
It	PRP	it
is	VBZ	be
the	DT	the
primary	JJ	primary
international	JJ	international
and	CC	and
long-haul	JJ	long-haul
gateway	NN	gateway
to	IN	to
the	DT	the
region	NN	region
.	.	.
</s>
<s type="decl">
Opened	VBN	open
in	IN	in
<date when="1962">
1962	CD	1962
</date>
to	TO	to
relieve	VB	relieve
Washington	NNP	Washington
National	NNP	National
Airport	NNP	Airport
(	-LRB-	(
now	RB	now
<ref target="Reagan%20National">
Reagan	NNP	Reagan
National	NNP	National
</ref>
)	-RRB-	)
,	,	,
it	PRP	it
soon	RB	soon
became	VBD	become
an	DT	a
enduring	JJ	enduring
mark	NN	mark
in	IN	in
the	DT	the
nation	NN	nation
's	POS	's
architecture	NN	architecture
.	.	.
</s>
</p>
<p>
<s type="decl">
The	DT	the
main	JJ	main
terminal	NN	terminal
,	,	,
designed	VBN	design
by	IN	by
Eero	NNP	Eero
Saarinen	NNP	Saarinen
,	,	,
is	VBZ	be
an	DT	a
architectural	JJ	architectural
masterpiece	NN	masterpiece
,	,	,
with	IN	with
a	DT	a
curved	JJ	curved
roof	NN	roof
that	WDT	that
arcs	VBZ	arc
gracefully	RB	gracefully
into	IN	into
air	NN	air
,	,	,
suspended	VBN	suspend
over	IN	over
a	DT	a
huge	JJ	huge
open	JJ	open
ticketing	NN	ticketing
and	CC	and
check-in	NN	check-in
area	NN	area
.	.	.
</s>
<s type="decl">
At	IN	at
one	CD	one
point	NN	point
,	,	,
this	DT	this
was	VBD	be
the	DT	the
only	JJ	only
building	NN	building
at	IN	at
the	DT	the
airport	NN	airport
,	,	,
and	CC	and
instead	RB	instead
of	IN	of
the	DT	the
usual	JJ	usual
affair	NN	affair
of	IN	of
the	DT	the
time	NN	time
where	WRB	where
passengers	NNS	passenger
walked	VBD	walk
to	IN	to
their	PRP$	their
plane	NN	plane
on	IN	on
the	DT	the
tarmac	NN	tarmac
,	,	,
special	JJ	special
shuttles	NNS	shuttle
known	VBN	know
as	IN	as
"	``	''
mobile	JJ	mobile
lounges	NNS	lounge
"	''	''
and	CC	and
"	``	''
plane	NN	plane
mates	NNS	mate
"	''	''
were	VBD	be
used	VBN	use
to	TO	to
ferry	VB	ferry
passengers	NNS	passenger
between	IN	between
the	DT	the
terminal	NN	terminal
and	CC	and
their	PRP$	their
planes	NNS	plane
.	.	.
</s>
</p>
<p>
<s type="decl">
Unfortunately	RB	unfortunately
the	DT	the
layout	NN	layout
has	VBZ	have
n't	RB	not
responded	VBN	respond
well	RB	well
to	IN	to
the	DT	the
changed	VBN	change
needs	NNS	need
of	IN	of
modern	JJ	modern
air	NN	air
travel	NN	travel
.	.	.
</s>
<s type="decl">
In	IN	in
order	NN	order
to	TO	to
accommodate	VB	accommodate
larger	JJR	large
jets	NNS	jet
and	CC	and
more	JJR	more
aerobridges	NNS	aerobridge
,	,	,
two	CD	2
satellite	NN	satellite
buildings	NNS	building
were	VBD	be
built	VBN	build
over	IN	over
time	NN	time
.	.	.
</s>
<s type="decl">
The	DT	the
layout	NN	layout
includes	VBZ	include
lengthy	JJ	lengthy
corridors	NNS	corridor
and	CC	and
long	JJ	long
escalators	NNS	escalator
and	CC	and
you	PRP	you
will	MD	will
have	VB	have
to	TO	to
take	VB	take
a	DT	a
train	NN	train
between	IN	between
the	DT	the
main	JJ	main
building	NN	building
and	CC	and
the	DT	the
concourses	NNS	concourse
-	:	-
expect	VB	expect
that	IN	that
you	PRP	you
will	MD	will
need	VB	need
some	DT	some
extra	JJ	extra
time	NN	time
to	TO	to
get	VB	get
to	IN	to
the	DT	the
gate	NN	gate
.	.	.
</s>
<s type="decl">
Many	JJ	many
carriers	NNS	carry
serve	VBP	serve
the	DT	the
airport	NN	airport
,	,	,
which	WDT	which
serves	VBZ	serve
as	IN	as
an	DT	a
East	NNP	East
Coast	NNP	Coast
hub	NN	hub
for	IN	for
United	NNP	Unite
Airlines	NNPS	Airline
and	CC	and
a	DT	a
major	JJ	major
gateway	NN	gateway
for	IN	for
Star	NNP	Star
Alliance	NNP	Alliance
airlines	NNS	airline
.	.	.
</s>
</p>
<p>
<s type="decl">
Now	RB	now
,	,	,
the	DT	the
main	JJ	main
terminal	NN	terminal
primarily	RB	primarily
houses	VBZ	house
ticket	NN	ticket
counters	NNS	counter
,	,	,
baggage	NN	baggage
claim	NN	claim
,	,	,
and	CC	and
security	NN	security
screening	NN	screening
,	,	,
with	IN	with
only	RB	only
a	DT	a
handful	NN	handful
of	IN	of
passenger	NN	passenger
gates	NNS	gate
,	,	,
while	IN	while
the	DT	the
vast	JJ	vast
majority	NN	majority
of	IN	of
flights	NNS	flight
arrive	VBP	arrive
and	CC	and
depart	VBP	depart
from	IN	from
the	DT	the
two	CD	2
midfield	NN	midfield
terminals	NNS	terminal
accessed	VBN	access
by	IN	by
train	NN	train
,	,	,
walkway	NN	walkway
,	,	,
or	CC	or
mobile	JJ	mobile
lounge	NN	lounge
.	.	.
</s>
</p>
<list type="unordered">
<item>
<s type="frag">
<ref target="http://www.flydulles.com/iad/airport-and-terminal-maps">
Detailed	JJ	detailed
map	NN	map
of	IN	of
terminal	NN	terminal
and	CC	and
concourses	NNS	concourse
</ref>
</s>
</item>
<item>
<s type="frag">
<ref target="https://maps.flydulles.com/">
Interactive	JJ	Interactive
map	NN	map
</ref>
</s>
</item>
</list>
<head>
<s type="frag">
Security	NN	Security
</s>
</head>
<p>
<s type="decl">
There	EX	there
are	VBP	be
two	CD	2
entrances	NNS	entrance
to	IN	to
the	DT	the
screening	NN	screening
area	NN	area
,	,	,
the	DT	the
West	NNP	West
and	CC	and
East	NNP	East
Security	NNP	Security
Checkpoints	NNPS	Checkpoint
.	.	.
</s>
</p>
<p>
<s type="decl">
TSA	NNP	TSA
PreCheck	NNP	PreCheck
and	CC	and
the	DT	the
private	JJ	private
service	NN	service
CLEAR	NNP	Clear
have	VBP	have
set	VBN	set
up	RP	up
their	PRP$	their
checkpoints	NNS	checkpoint
for	IN	for
departing	VBG	depart
passengers	NNS	passenger
in	IN	in
between	IN	between
the	DT	the
two	CD	2
general	JJ	general
checkpoints	NNS	checkpoint
.	.	.
</s>
</p>
<head>
<s type="frag">
Flights	NNS	flight
</s>
</head>
<list type="unordered">
<item>
<s type="frag">
<hi rend="bold">
Concourse	NNP	Concourse
A	NN	A
</hi>
</s>
</item>
</list>
<list type="unordered">
<item>
<s type="frag">
United	NNP	Unite
Express	NNP	Express
</s>
</item>
<item>
<s type="frag">
<hi rend="italic">
International	JJ	International
Departures	NNPS	Departures
:	:	:
</hi>
Air	NNP	Air
China	NNP	China
,	,	,
Copa	NNP	Copa
,	,	,
Ethiopian	NNP	Ethiopian
</s>
</item>
</list>
<list type="unordered">
<item>
<s type="frag">
<hi rend="bold">
Concourse	NNP	Concourse
B	CD	B
</hi>
</s>
</item>
</list>
<list type="unordered">
<item>
<s type="frag">
<hi rend="italic">
International	JJ	International
Departures	NNPS	Departures
:	:	:
</hi>
Air	NNP	Air
India	NNP	India
,	,	,
ANA	NNP	ANA
,	,	,
Austrian	NNP	Austrian
,	,	,
Avianca	NNP	Avianca
,	,	,
Brussels	NNP	Brussels
Airlines	NNPS	Airline
,	,	,
Lufthansa	NNP	Lufthansa
,	,	,
SAS	NNP	SAS
,	,	,
South	NNP	South
African	NNP	African
,	,	,
Turkish	NNP	Turkish
Airlines	NNPS	Airline
</s>
</item>
<item>
<s type="frag">
Aer	NNP	Aer
Lingus	NNP	Lingus
(	-LRB-	(
all	DT	all
flights	NNS	flight
,	,	,
due	JJ	due
to	IN	to
preclearance	NN	preclearance
)	-RRB-	)
</s>
</item>
</list>
<list type="unordered">
<item>
<s type="frag">
<hi rend="bold">
Concourse	NNP	Concourse
C	CD	C
</hi>
</s>
</item>
</list>
<list type="unordered">
<item>
<s type="frag">
United	NNP	Unite
and	CC	and
United	NNP	Unite
Express	NNP	Express
only	RB	only
,	,	,
as	RB	as
well	RB	well
as	IN	as
processing	NN	processing
for	IN	for
international	JJ	international
Star	NNP	Star
Alliance	NNP	Alliance
arrivals	NNS	arrival
</s>
</item>
</list>
<list type="unordered">
<item>
<s type="frag">
<hi rend="bold">
Concourse	NNP	Concourse
D	CD	D
</hi>
</s>
</item>
</list>
<list type="unordered">
<item>
<s type="frag">
United	NNP	Unite
and	CC	and
United	NNP	Unite
Express	NNP	Express
only	RB	only
</s>
</item>
</list>
<list type="unordered">
<item>
<s type="frag">
<hi rend="bold">
Concourse	NNP	Concourse
H	CD	H
</hi>
</s>
</item>
</list>
<list type="unordered">
<item>
<s type="frag">
Waiting	VBG	wait
area	NN	area
for	IN	for
airlines	NNS	airline
with	IN	with
only	RB	only
plane	NN	plane
mates	NNS	mate
</s>
</item>
</list>
<list type="unordered">
<item>
<s type="frag">
<hi rend="bold">
Concourse	NNP	Concourse
Z	NN	Z
</hi>
</s>
</item>
</list>
<list type="unordered">
<item>
<s type="frag">
Air	NNP	Air
Canada	NNP	Canada
(	-LRB-	(
all	DT	all
flights	NNS	flight
due	JJ	due
to	IN	to
preclearance	NN	preclearance
)	-RRB-	)
,	,	,
Frontier	NNP	Frontier
</s>
</item>
</list>
<list type="unordered">
<item>
<s type="frag">
<hi rend="bold">
International	NNP	International
Arrivals	NNP	Arrival
Building	NNP	Building
(	-LRB-	(
IAB	NNP	IAB
)	-RRB-	)
</hi>
</s>
</item>
</list>
<list type="unordered">
<item>
<s type="frag">
Gate	NNP	Gate
for	IN	for
<hi rend="bold">
almost	RB	almost
all	DT	all
international	JJ	international
flights	NNS	flight
arriving	VBG	arrive
</hi>
at	IN	at
Dulles	NNP	Dulles
,	,	,
with	IN	with
the	DT	the
exception	NN	exception
of	IN	of
pre-clearance	NN	pre-clearance
flights	NNS	flight
and	CC	and
Star	NNP	Star
Alliance	NNP	Alliance
flights	NNS	flight
.	.	.
</s>
<s type="decl">
This	DT	this
building	NN	building
uses	VBZ	use
plane	NN	plane
mates	NNS	mate
to	TO	to
take	VB	take
passengers	NNS	passenger
from	IN	from
the	DT	the
plane	NN	plane
to	IN	to
the	DT	the
building	NN	building
fr	NN	fruil
processing	NN	processing
.	.	.
</s>
</item>
</list>
<head>
<s type="frag">
Departure	NN	departure
</s>
</head>
<p>
<s type="decl">
Each	DT	each
airline	NN	airline
has	VBZ	have
a	DT	a
specific	JJ	specific
location	NN	location
for	IN	for
their	PRP$	their
<hi rend="bold">
check-in	NN	check-in
counters	NNS	counter
</hi>
:	:	:
</s>
</p>
<list type="unordered">
<item>
<s type="frag">
<hi rend="bold">
Ticket	NN	ticket
Counter	NN	counter
1	CD	1
</hi>
</s>
</item>
</list>
<list type="unordered">
<item>
<s type="frag">
Aer	NNP	Aer
Lingus	NNP	Lingus
,	,	,
Aeroflot	NNP	Aeroflot
,	,	,
Aeromexico	NNP	Aeromexico
,	,	,
Air	NNP	Air
China	NNP	China
,	,	,
Air	NNP	Air
India	NNP	India
,	,	,
British	NNP	British
Airways	NNPS	Airway
,	,	,
Delta	NNP	Delta
,	,	,
Ethiopian	NNP	Ethiopian
,	,	,
Etihad	NNP	Etihad
,	,	,
Primera	NNP	Primera
,	,	,
Porter	NNP	Porter
,	,	,
Southwest	NNP	Southwest
,	,	,
Volaris	NNP	Volaris
</s>
</item>
</list>
<list type="unordered">
<item>
<s type="frag">
<hi rend="bold">
Ticket	NN	ticket
Counter	NN	counter
2	CD	2
</hi>
</s>
</item>
</list>
<list type="unordered">
<item>
<s type="frag">
Air	NNP	Air
France	NNP	France
,	,	,
American	NNP	American
,	,	,
Brussels	NNP	Brussels
,	,	,
Copa	NNP	Copa
,	,	,
Emirates	NNPS	Emirate
,	,	,
KLM	NNP	KLM
,	,	,
Korean	NNP	Korean
Air	NNP	Air
,	,	,
Qatar	NNP	Qatar
,	,	,
Royal	NNP	Royal
Air	NNP	Air
Maroc	NNP	Maroc
,	,	,
Saudia	NNP	Saudia
,	,	,
Virgin	NNP	Virgin
Atlantic	NNP	Atlantic
</s>
</item>
</list>
<list type="unordered">
<item>
<s type="frag">
<hi rend="bold">
Ticket	NN	ticket
Counter	NN	counter
3	CD	3
</hi>
</s>
</item>
</list>
<list type="unordered">
<item>
<s type="frag">
Air	NNP	Air
Canada	NNP	Canada
,	,	,
Alaska	NNP	Alaska
,	,	,
ANA	NNP	ANA
,	,	,
Austrian	NNP	Austrian
,	,	,
Avancia	NNP	Avancia
,	,	,
Frontier	NNP	Frontier
,	,	,
Icelandair	NNP	Icelandair
,	,	,
jetBlue	NNP	jetBlue
,	,	,
Lufthansa	NNP	Lufthansa
,	,	,
SAS	NNP	SAS
,	,	,
South	NNP	South
African	NNP	African
,	,	,
Turkish	NNP	Turkish
</s>
</item>
</list>
<list type="unordered">
<item>
<s type="frag">
<hi rend="bold">
Ticket	NN	ticket
Counter	NN	counter
4	CD	4
</hi>
</s>
</item>
</list>
<list type="unordered">
<item>
<s type="frag">
United	NNP	Unite
and	CC	and
United	NNP	Unite
Express	NNP	Express
</s>
<s type="intj">
only	RB	only
</s>
</item>
</list>
<p>
<s type="decl">
The	DT	the
ticket	NN	ticket
counter	NN	counter
numbers	NNS	number
are	VBP	be
designated	VBN	designate
by	IN	by
the	DT	the
<hi rend="bold">
order	NN	order
you	PRP	you
pass	VBP	pass
them	PRP	they
</hi>
as	IN	as
you	PRP	you
drive	VBP	drive
into	IN	into
the	DT	the
airport	NN	airport
complex	NN	complex
.	.	.
</s>
<s type="sub">
For	IN	for
example	NN	example
,	,	,
Counter	NNP	Counter
2	CD	2
would	MD	would
be	VB	be
the	DT	the
second	JJ	second
counter	NN	counter
complex	NN	complex
passed	VBN	pass
.	.	.
</s>
<s type="decl">
This	DT	this
also	RB	also
means	VBZ	mean
that	IN	that
the	DT	the
counter	NN	counter
numbers	NNS	number
are	VBP	be
ordered	VBN	order
in	IN	in
a	DT	a
west	NN	west
to	IN	to
east	JJ	east
fashion	NN	fashion
(	-LRB-	(
ex	NN	ex
.	.	.
1	CD	1
is	VBZ	be
the	DT	the
westernmost	JJS	westernmost
counter	NN	counter
and	CC	and
4	CD	4
is	VBZ	be
the	DT	the
easternmost	JJS	easternmost
)	-RRB-	)
.	.	.
</s>
<s type="decl">
Entering	VBG	enter
the	DT	the
airport	NN	airport
means	VBZ	mean
that	IN	that
you	PRP	you
are	VBP	be
facing	VBG	face
a	DT	a
southerly	JJ	southerly
direction	NN	direction
,	,	,
so	RB	so
keep	VB	keep
that	DT	that
in	IN	in
mind	NN	mind
when	WRB	when
looking	VBG	look
for	IN	for
your	PRP$	your
counter	NN	counter
.	.	.
</s>
</p>
<p>
<s type="decl">
The	DT	the
airport	NN	airport
has	VBZ	have
drop	NN	drop
off	RP	off
zones	NNS	zone
at	IN	at
each	DT	each
counter	NN	counter
,	,	,
so	RB	so
you	PRP	you
can	MD	can
stop	VB	stop
at	IN	at
the	DT	the
zone	NN	zone
corresponding	VBG	correspond
to	IN	to
the	DT	the
number	NN	number
of	IN	of
your	PRP$	your
counter	NN	counter
.	.	.
</s>
</p>
<head>
<s type="frag">
Arrival	NN	Arrival
</s>
</head>
<p>
<s type="decl">
Some	DT	some
airlines	NNS	airline
have	VBP	have
specific	JJ	specific
<hi rend="bold">
baggage	NN	baggage
claims	NNS	claim
</hi>
for	IN	for
arriving	VBG	arrive
passengers	NNS	passenger
:	:	:
</s>
</p>
<list type="unordered">
<item>
<s type="frag">
<hi rend="bold">
Claims	NNS	claim
1-5	CD	1-5
</hi>
-	:	-
United	NNP	Unite
</s>
</item>
<item>
<hi rend="bold">
<s type="frag">
Claims	NNS	claim
</s>
<s type="frag">
6	CD	6
</s>
</hi>
<s type="frag">
-	:	-
United	NNP	Unite
,	,	,
Aer	NNP	Aer
Lingus	NNP	Lingus
</s>
</item>
<item>
<s type="frag">
<hi rend="bold">
Claim	NN	Claim
7	CD	7
</hi>
-	:	-
Frontier	NNP	Frontier
</s>
</item>
<item>
<s type="frag">
<hi rend="bold">
Claim	NNP	Claim
8	CD	8
</hi>
-	:	-
special	JJ	special
claim	NN	claim
for	IN	for
oversized	JJ	oversized
baggage	NN	baggage
</s>
</item>
<item>
<s type="frag">
<hi rend="bold">
Claim	NN	Claim
10	CD	10
</hi>
-	:	-
jetBlue	NNP	jetBlue
</s>
</item>
<item>
<s type="frag">
<hi rend="bold">
Claims	NNS	claim
11-12	CD	11-12
</hi>
-	:	-
American	JJ	American
,	,	,
Ethiad	NNP	Ethiad
</s>
</item>
<item>
<s type="frag">
<hi rend="bold">
Claims	NNS	claim
13-14	CD	13-14
</hi>
-	:	-
Delta	NNP	Delta
,	,	,
Southwest	NNP	Southwest
</s>
</item>
<item>
<s type="frag">
<hi rend="bold">
Claim	NN	Claim
15	CD	15
</hi>
-	:	-
All	DT	all
<hi rend="bold">
international	JJ	international
arrivals	NNS	arrival
</hi>
except	IN	except
for	IN	for
preclearance	NN	preclearance
flights	NNS	flight
</s>
</item>
</list>
<p>
<s type="decl">
There	EX	there
is	VBZ	be
no	DT	no
Claim	NN	Claim
</s>
<s type="frag">
9	CD	9
.	.	.
</s>
</p>
<head>
<s type="frag">
Customs	NNS	custom
</s>
</head>
<p>
<s type="frag">
<hi rend="bold">
Star	NNP	Star
Alliance	NNP	Alliance
international	JJ	international
arrivals	NNS	arrival
</hi>
</s>
<s type="imp">
arrive	VB	arrive
at	IN	at
the	DT	the
C	NNP	C
concourse	NN	concourse
,	,	,
where	WRB	where
you	PRP	you
go	VBP	go
via	IN	via
a	DT	a
secure	JJ	secure
hallway	NN	hallway
between	IN	between
the	DT	the
sterile	JJ	sterile
area	NN	area
and	CC	and
the	DT	the
windows	NNS	window
on	IN	on
the	DT	the
edge	NN	edge
of	IN	of
the	DT	the
concourse	NN	concourse
to	IN	to
the	DT	the
east	JJ	east
end	NN	end
.	.	.
</s>
<s type="decl">
There	RB	there
,	,	,
you	PRP	you
go	VBP	go
through	IN	through
customs	NNS	custom
.	.	.
</s>
<s type="sub">
At	IN	at
Dulles	NNP	Dulles
,	,	,
if	IN	if
you	PRP	you
get	VBP	get
an	DT	a
orange	JJ	orange
box	NN	box
at	IN	at
passport	NN	passport
control	NN	control
,	,	,
you	PRP	you
must	MD	must
go	VB	go
to	IN	to
a	DT	a
secondary	JJ	secondary
screening	NN	screening
room	NN	room
with	IN	with
your	PRP$	your
bags	NNS	bag
.	.	.
</s>
<s type="decl">
Otherwise	RB	otherwise
,	,	,
you	PRP	you
can	MD	can
simply	RB	simply
take	VB	take
your	PRP$	your
checked	VBN	check
bags	NNS	bag
off	IN	off
the	DT	the
conveyor	NN	conveyor
and	CC	and
recheck	VB	recheck
them	PRP	they
after	IN	after
walking	VBG	walk
about	RB	about
50	CD	50
feet	NNS	foot
(	-LRB-	(
dogs	NNS	dog
will	MD	will
sniff	VB	sniff
your	PRP$	your
bag	NN	bag
along	IN	along
the	DT	the
way	NN	way
)	-RRB-	)
.	.	.
</s>
<s type="decl">
Afterwards	RB	afterwards
,	,	,
you	PRP	you
reclear	VBP	reclear
security	NN	security
.	.	.
</s>
<s type="decl">
There	EX	there
are	VBP	be
separate	JJ	separate
lines	NNS	line
for	IN	for
U.S./Canadian	NNP	U.S./Canadian
and	CC	and
foreign	JJ	foreign
nationals	NNS	national
,	,	,
the	DT	the
former	JJ	former
getting	VBG	get
TSA	NNP	TSA
Precheck	NNP	Precheck
automatically	RB	automatically
and	CC	and
thus	RB	thus
will	MD	will
not	RB	not
have	VB	have
to	TO	to
remove	VB	remove
their	PRP$	their
belts	NNS	belt
and	CC	and
shoes	NNS	shoe
.	.	.
</s>
</p>
<head>
<s type="frag">
Public	JJ	Public
transit	NN	transit
</s>
</head>
<list type="unordered">
<item>
<s type="decl">
<hi rend="bold">
<ref target="http://www.flydulles.com/iad/silver-line-express-bus-metrorail-station">
The	DT	the
Silver	NNP	Silver
Line	NNP	Line
Express	NNP	Express
Bus	NNP	Bus
</ref>
</hi>
operates	VBZ	operate
every	DT	every
15	CD	15
minutes	NNS	minute
between	IN	between
the	DT	the
airport	NN	airport
and	CC	and
the	DT	the
garage	NN	garage
near	IN	near
the	DT	the
Wiehle-Reston	NNP	Wiehle-Reston
East	NNP	East
Metrorail	NNP	Metrorail
Station	NNP	Station
(	-LRB-	(
Silver	NNP	Silver
Line	NNP	Line
)	-RRB-	)
.	.	.
</s>
<s type="decl">
The	DT	the
bus	NN	bus
journey	NN	journey
takes	VBZ	take
10	CD	10
minutes	NNS	minute
and	CC	and
costs	VBZ	cost
$	SYM	$
5	CD	5
.	.	.
</s>
<s type="decl">
From	IN	from
there	RB	there
,	,	,
after	IN	after
crossing	VBG	cross
the	DT	the
pedestrian	NN	pedestrian
bridge	NN	bridge
over	IN	over
the	DT	the
highway	NN	highway
to	TO	to
reach	VB	reach
the	DT	the
Metrorail	NNP	Metrorail
station	NN	station
,	,	,
the	DT	the
journey	NN	journey
by	IN	by
Metrorail	NNP	Metrorail
to	IN	to
the	DT	the
<ref target="Washington%2C%20D.C./East%20End">
East	NNP	East
End	NNP	end
</ref>
takes	VBZ	take
another	DT	another
45	CD	45
minutes	NNS	minute
.	.	.
</s>
<s type="decl">
A	DT	a
cheaper	JJR	cheap
but	CC	but
slower	JJR	slow
option	NN	option
to	TO	to
get	VB	get
from	IN	from
the	DT	the
airport	NN	airport
to	IN	to
the	DT	the
garage	NN	garage
near	IN	near
the	DT	the
Metrorail	NNP	Metrorail
station	NN	station
is	VBZ	be
to	TO	to
take	VB	take
<ref target="http://www.fairfaxcounty.gov/connector/routes/">
Fairfax	NNP	Fairfax
Connector	NNP	Connector
</ref>
Bus	NNP	Bus
Routes	NNPS	Routes
981/983	CD	981/983
which	WDT	which
depart	VBP	depart
the	DT	the
airport	NN	airport
every	DT	every
20	CD	20
minutes	NNS	minute
from	IN	from
<time from="0900" to="1900">
9AM-7PM	NNP	9AM-7PM
</time>
and	CC	and
every	DT	every
40	CD	40
minutes	NNS	minute
from	IN	from
<time when="0600">
6AM-9AM	NNP	6AM-9AM
</time>
and	CC	and
<time when="2300">
7PM-11PM	CD	7PM-11PM
</time>
.	.	.
</s>
<s type="decl">
The	DT	the
bus	NN	bus
journey	NN	journey
takes	VBZ	take
30	CD	30
minutes	NNS	minute
and	CC	and
costs	VBZ	cost
$	SYM	$
2.00	CD	2.00
.	.	.
</s>
<s type="decl">
The	DT	the
Silver	NNP	Silver
Line	NNP	Line
of	IN	of
the	DT	the
Metrorail	NNP	Metrorail
is	VBZ	be
being	VBG	be
extended	VBN	extend
to	IN	to
the	DT	the
airport	NN	airport
;	:	;
however	RB	however
,	,	,
the	DT	the
projected	VBN	project
completion	NN	completion
date	NN	date
is	VBZ	be
in	IN	in
<date when="2021">
2021	CD	2021
</date>
.	.	.
</s>
</item>
<item>
<s type="decl">
<hi rend="bold">
<ref target="https://www.wmata.com/schedules/timetables/">
Metrobus	NNP	Metrobus
5A	NNP	5A
</ref>
</hi>
makes	VBZ	make
stops	NNS	stop
in	IN	in
<ref target="Herndon">
Herndon	NNP	Herndon
</ref>
,	,	,
<ref target="Tysons%20Corner">
Tysons	NNP	Tyson
Corner	NNP	Corner
</ref>
,	,	,
Rosslyn	NNP	Rosslyn
Metrorail	NNP	Metrorail
Station	NNP	Station
(	-LRB-	(
Blue/Orange/Silver	NNP	Blue/Orange/Silver
Lines	NNPS	Lines
)	-RRB-	)
,	,	,
and	CC	and
L'Enfant	NNP	L'Enfant
Plaza	NNP	Plaza
Metrorail	NNP	Metrorail
Station	NNP	Station
(	-LRB-	(
Green/Yellow/Blue/Orange/Silver	NNP	Green/Yellow/Blue/Orange/Silver
Lines	NNPS	Lines
)	-RRB-	)
,	,	,
a	DT	a
few	JJ	few
blocks	NNS	block
south	RB	south
of	IN	of
the	DT	the
<ref target="Washington%2C%20D.C./National%20Mall">
National	NNP	National
Mall	NNP	Mall
</ref>
.	.	.
</s>
<s type="decl">
It	PRP	it
generally	RB	generally
departs	VBZ	depart
from	IN	from
the	DT	the
airport	NN	airport
every	DT	every
40	CD	40
minutes	NNS	minute
on	IN	on
weekdays	NNS	weekday
and	CC	and
hourly	RB	hourly
(	-LRB-	(
though	IN	though
not	RB	not
on	IN	on
the	DT	the
hour	NN	hour
)	-RRB-	)
on	IN	on
weekends	NNS	weekend
,	,	,
taking	VBG	take
40-50	CD	40-50
minutes	NNS	minute
to	IN	to
the	DT	the
Rosslyn	NNP	Rosslyn
Metrorail	NNP	Metrorail
Station	NNP	Station
and	CC	and
50-60	CD	50-60
minutes	NNS	minute
to	IN	to
the	DT	the
L'Enfant	NNP	L'Enfant
Plaza	NNP	Plaza
Metrorail	NNP	Metrorail
Station	NNP	Station
.	.	.
</s>
<s type="decl">
The	DT	the
fare	NN	fare
is	VBZ	be
$	SYM	$
7.50	CD	7.50
one-way	JJ	one-way
(	-LRB-	(
no	DT	no
change	NN	change
given	VBN	give
)	-RRB-	)
.	.	.
</s>
<s type="decl">
The	DT	the
bus	NN	bus
stops	VBZ	stop
near	IN	near
Curb	NNP	Curb
2E	CD	2E
outside	RB	outside
of	IN	of
the	DT	the
airport	NN	airport
terminal	NN	terminal
.	.	.
</s>
</item>
<item>
<s type="frag">
<hi rend="bold">
<ref target="https://www.fairfaxcounty.gov/connector/sites/connector/files/assets/documents/pdf/route%2520pdfs/route_981-983_012415_web.pdf">
Fairfax	NNP	Fairfax
Connector	NNP	Connector
Bus	NNP	Bus
#983	CD	#983
</ref>
</hi>
to	IN	to
the	DT	the
<ref target="http://airandspace.si.edu/visit/udvar-hazy-center/">
Smithsonian	NNP	Smithsonian
National	NNP	National
Air	NNP	Air
and	CC	and
Space	NNP	Space
Museum	NNP	Museum
's	POS	's
Udvar-Hazy	NNP	Udvar-Hazy
Center	NNP	Center
</ref>
.	.	.
</s>
<s type="decl">
The	DT	the
bus	NN	bus
departs	VBZ	depart
from	IN	from
the	DT	the
airport	NN	airport
every	DT	every
20	CD	20
minutes	NNS	minute
daily	RB	daily
,	,	,
costing	VBG	cost
$	SYM	$
2.00	CD	2.00
and	CC	and
taking	VBG	take
12	CD	12
minutes	NNS	minute
to	TO	to
reach	VB	reach
the	DT	the
museum	NN	museum
.	.	.
</s>
</item>
</list>
</text>