<?xml version='1.0' encoding='utf8'?>
<text id="AMALGUM_voyage_tepoztlan" title="Tepoztlan" shortTitle="tepoztlan" author="Wikivoyage community (see URL)" type="voyage" dateCollected="2019-11-01" sourceURL="https://en.wikivoyage.org/wiki?curid=35618" speakerList="none" speakerCount="0">
<head>
<s type="frag">
Tepoztlan	NNP	Tepoztlan
</s>
</head>
<p>
<s type="decl">
<hi rend="bold">
Tepoztlan	NNP	Tepoztlan
</hi>
is	VBZ	be
a	DT	a
popular	JJ	popular
tourist	NN	tourist
destination	NN	destination
an	DT	a
hour	NN	hour
south	RB	south
of	IN	of
<ref target="Mexico%20City">
Mexico	NNP	Mexico
City	NNP	City
</ref>
.	.	.
</s>
<s type="decl">
It	PRP	it
's	VBZ	be
famous	JJ	famous
for	IN	for
the	DT	the
El	NNP	El
Tepezteco	NNP	Tepezteco
pyramid	NN	pyramid
,	,	,
which	WDT	which
is	VBZ	be
on	IN	on
the	DT	the
summit	NN	summit
of	IN	of
the	DT	the
nearby	JJ	nearby
Tepezteco	NNP	Tepezteco
Mountain	NNP	Mountain
.	.	.
</s>
<s type="decl">
It	PRP	it
's	VBZ	be
also	RB	also
known	VBN	know
for	IN	for
its	PRP$	its
spas	NNS	spa
,	,	,
meditation	NN	meditation
,	,	,
alternative	JJ	alternative
medicine	NN	medicine
clinics	NNS	clinic
and	CC	and
a	DT	a
very	RB	very
traditional	JJ	traditional
city	NN	city
center	NN	center
.	.	.
</s>
<s type="decl">
It	PRP	it
is	VBZ	be
a	DT	a
small	JJ	small
town	NN	town
so	RB	so
you	PRP	you
do	VBP	do
n't	RB	not
need	VB	need
a	DT	a
car	NN	car
to	TO	to
travel	VB	travel
within	IN	within
the	DT	the
city	NN	city
.	.	.
</s>
</p>
<head>
<s type="imp">
Get	VB	get
in	RB	in
</s>
</head>
<p>
<s type="decl">
From	IN	from
Mexico	NNP	Mexico
City	NNP	City
,	,	,
you	PRP	you
may	MD	may
take	VB	take
the	DT	the
metro	NN	metro
to	IN	to
the	DT	the
Tasqueña	NNP	Tasqueña
station	NN	station
and	CC	and
follow	VB	follow
the	DT	the
"	``	''
autobuses	NNS	autobus
"	''	''
signs	NNS	sign
to	IN	to
the	DT	the
southern	JJ	southern
bus	NN	bus
depot	NN	depot
next	JJ	next
door	NN	door
.	.	.
</s>
<s type="decl">
The	DT	the
various	JJ	various
bus	NN	bus
companies	NNS	company
display	VBP	display
their	PRP$	their
destinations	NNS	destination
and	CC	and
times	NNS	time
.	.	.
</s>
<s type="decl">
Pullman	NNP	Pullman
de	NNP	de
Morelos	NNP	Morelos
offers	VBZ	offer
bus	NN	bus
service	NN	service
every	DT	every
30	CD	30
minutes	NNS	minute
and	CC	and
a	DT	a
one-way	JJ	one-way
ticket	NN	ticket
cost	VBD	cost
M$	NN	M$
134	CD	134
(	-LRB-	(
<ref target="Mexico%23Currency">
pesos	NN	peso
</ref>
)	-RRB-	)
in	IN	in
<date when="2018">
2018	CD	2018
</date>
.	.	.
</s>
<s type="decl">
The	DT	the
bus	NN	bus
ride	NN	ride
is	VBZ	be
comfortable	JJ	comfortable
,	,	,
scenic	JJ	scenic
and	CC	and
takes	VBZ	take
about	RB	about
an	DT	a
hour	NN	hour
and	CC	and
a	DT	a
half	NN	half
(	-LRB-	(
depending	VBG	depend
on	IN	on
traffic	NN	traffic
)	-RRB-	)
.	.	.
</s>
<s type="decl">
Upon	IN	upon
arrival	NN	arrival
in	IN	in
Tepoztlan	NNP	Tepoztlan
,	,	,
the	DT	the
bus	NN	bus
may	MD	may
drop	VB	drop
you	PRP	you
at	IN	at
a	DT	a
depot	NN	depot
on	IN	on
the	DT	the
edge	NN	edge
of	IN	of
town	NN	town
.	.	.
</s>
<s type="decl">
Taxis	NNS	taxis
will	MD	will
be	VB	be
waiting	VBG	wait
to	TO	to
take	VB	take
you	PRP	you
to	IN	to
the	DT	the
main	JJ	main
square	NN	square
for	IN	for
M$	NNP	M$
40	CD	40
.	.	.
</s>
<s type="decl">
Walking	VBG	Walk
to	IN	to
the	DT	the
center	NN	center
will	MD	will
take	VB	take
20-30	CD	20-30
minutes	NNS	minute
or	CC	or
so	RB	so
.	.	.
</s>
<s type="decl">
The	DT	the
path	NN	path
to	TO	to
walk	VB	walk
downtown	NN	downtown
is	VBZ	be
marked	VBN	mark
by	IN	by
a	DT	a
red	JJ	red
metal	NN	metal
guard	NN	guard
rail	NN	rail
across	RB	across
from	IN	from
the	DT	the
bus	NN	bus
station	NN	station
.	.	.
</s>
</p>
<p>
<s type="decl">
Frequent	JJ	Frequent
buses	NNS	bus
run	VBP	run
to	IN	to
and	CC	and
from	IN	from
the	DT	the
Adolfo	NNP	Adolfo
Lopez	NNP	Lopez
Mateos	NNP	Mateos
market	NN	market
in	IN	in
Cuernavaca	NNP	Cuernavaca
and	CC	and
pick	VBP	pick
up	RP	up
passengers	NNS	passenger
along	IN	along
the	DT	the
way	NN	way
to	IN	to
the	DT	the
center	NN	center
of	IN	of
Tepoztlan	NNP	Tepoztlan
.	.	.
</s>
<s type="frag">
About	RB	about
MX$	NNP	MX$
20	CD	20
.	.	.
</s>
</p>
<head>
<s type="imp">
Get	VB	get
around	RB	around
</s>
</head>
<p>
<s type="decl">
Tepoztlan	NNP	Tepoztlan
is	VBZ	be
a	DT	a
small	JJ	small
quaint	JJ	quaint
town	NN	town
and	CC	and
is	VBZ	be
easily	RB	easily
walkable	JJ	walkable
.	.	.
</s>
<s type="decl">
Most	JJS	most
of	IN	of
the	DT	the
activity	NN	activity
is	VBZ	be
centered	VBN	center
around	IN	around
its	PRP$	its
main	JJ	main
square	NN	square
and	CC	and
along	IN	along
the	DT	the
main	JJ	main
avenue	NN	avenue
,	,	,
Avenida	NNP	Avenida
5	CD	5
de	NNP	de
mayo	NNP	mayo
.	.	.
</s>
<s type="decl">
There	EX	there
is	VBZ	be
local	JJ	local
bus	NN	bus
service	NN	service
to	IN	to
surrounding	VBG	surround
towns	NNS	town
.	.	.
</s>
</p>
<head>
<s type="imp">
See	VB	see
</s>
</head>
<p>
<s type="decl">
There	EX	there
is	VBZ	be
an	DT	a
archeological	JJ	archeological
site	NN	site
at	IN	at
the	DT	the
top	NN	top
of	IN	of
an	DT	a
easy-hikeable	JJ	easy-hikeable
mountain	NN	mountain
(	-LRB-	(
assuming	VBG	assume
you	PRP	you
are	VBP	be
in	IN	in
decent	JJ	decent
shape	NN	shape
--	:	-
there	EX	there
are	VBP	be
400m	CD	400m
of	IN	of
stairs	NNS	stair
)	-RRB-	)
that	WDT	that
is	VBZ	be
also	RB	also
famous	JJ	famous
for	IN	for
its	PRP$	its
"	``	''
good	JJ	good
vibrations	NNS	vibration
"	''	''
.	.	.
</s>
<s type="decl">
The	DT	the
hike	NN	hike
can	MD	can
take	VB	take
up	IN	up
to	IN	to
2	CD	2
hours	NNS	hour
depending	VBG	depend
on	IN	on
your	PRP$	your
fitness	NN	fitness
level	NN	level
.	.	.
</s>
<s type="decl">
The	DT	the
pyramid	NN	pyramid
,	,	,
<hi rend="bold">
El	NNP	El
Tepozteco	NNP	Tepozteco
</hi>
,	,	,
offers	VBZ	offer
wonderful	JJ	wonderful
views	NNS	view
of	IN	of
the	DT	the
surrounding	VBG	surround
area	NN	area
.	.	.
</s>
<s type="decl">
The	DT	the
site	NN	site
may	MD	may
be	VB	be
reached	VBN	reach
by	IN	by
walking	VBG	walk
down	IN	down
Avenida	NNP	Avenida
5	CD	5
de	NNP	de
mayo	NNP	mayo
(	-LRB-	(
in	IN	in
the	DT	the
direction	NN	direction
away	RB	away
from	IN	from
where	WRB	where
you	PRP	you
entered	VBD	enter
the	DT	the
town	NN	town
)	-RRB-	)
.	.	.
</s>
<s type="imp">
Continue	VB	continue
until	IN	until
the	DT	the
street	NN	street
ends	VBZ	end
to	IN	to
the	DT	the
steps	NNS	step
which	WDT	which
mark	VBP	mark
the	DT	the
beginning	NN	beginning
of	IN	of
the	DT	the
trail	NN	trail
.	.	.
</s>
<s type="imp">
Make	VB	make
sure	JJ	sure
to	TO	to
bring	VB	bring
water	NN	water
with	IN	with
you	PRP	you
.	.	.
</s>
<s type="decl">
The	DT	the
hike	NN	hike
to	IN	to
the	DT	the
top	NN	top
is	VBZ	be
free	JJ	free
but	CC	but
it	PRP	it
will	MD	will
cost	VB	cost
M$	RB	M$
37	CD	37
(	-LRB-	(
in	IN	in
<date when="2010">
2010	CD	2010
</date>
)	-RRB-	)
to	TO	to
access	VB	access
the	DT	the
pyramid	NN	pyramid
.	.	.
</s>
<s type="decl">
At	IN	at
the	DT	the
top	NN	top
you	PRP	you
will	MD	will
also	RB	also
encounter	VB	encounter
coati	NN	coati
,	,	,
also	RB	also
known	VBN	know
as	IN	as
a	DT	a
tejón	NN	tejón
.	.	.
</s>
<s type="decl">
These	DT	this
animals	NNS	animal
,	,	,
members	NNS	member
of	IN	of
the	DT	the
raccoon	NN	raccoon
family	NN	family
,	,	,
are	VBP	be
curious	JJ	curious
and	CC	and
will	MD	will
attempt	VB	attempt
to	TO	to
open	VB	open
backpacks	NNS	backpack
to	TO	to
find	VB	find
food	NN	food
.	.	.
</s>
</p>
<p>
<s type="decl">
There	EX	there
is	VBZ	be
also	RB	also
a	DT	a
beautiful	JJ	beautiful
former	JJ	former
convent	NN	convent
called	VBN	call
<hi rend="bold">
Dominico	NNP	Dominico
de	NNP	de
la	NNP	la
Navidad	NNP	Navidad
</hi>
.	.	.
</s>
<s type="decl">
It	PRP	it
has	VBZ	have
been	VBN	be
restored	VBN	restore
and	CC	and
entrance	NN	entrance
is	VBZ	be
free	JJ	free
.	.	.
</s>
<s type="decl">
It	PRP	it
is	VBZ	be
located	VBN	locate
right	RB	right
off	IN	off
the	DT	the
main	JJ	main
square	NN	square
.	.	.
</s>
</p>
<p>
<s type="decl">
If	IN	if
you	PRP	you
are	VBP	be
curious	JJ	curious
about	IN	about
it	PRP	it
,	,	,
the	DT	the
locals	NNS	local
claim	VBP	claim
UFO	NNP	UFO
sightings	NNS	sighting
are	VBP	be
common	JJ	common
,	,	,
which	WDT	which
mostly	RB	mostly
just	RB	just
adds	VBZ	add
to	IN	to
the	DT	the
"	``	''
new	JJ	new
age	NN	age
"	''	''
vibe	NN	vibe
of	IN	of
the	DT	the
town	NN	town
.	.	.
</s>
<s type="imp">
Ask	VB	ask
about	IN	about
the	DT	the
"	``	''
ovni	NN	ovni
"	''	''
to	TO	to
hear	VB	hear
strange	JJ	strange
tales	NNS	tale
.	.	.
</s>
</p>
<head>
<s type="imp">
Do	VB	do
</s>
</head>
<p>
<s type="decl">
<hi rend="bold">
Temazcal	NNP	Temazcal
</hi>
is	VBZ	be
an	DT	a
ancient	JJ	ancient
Mexican	JJ	Mexican
therapy	NN	therapy
that	WDT	that
consists	VBZ	consist
of	IN	of
a	DT	a
little	JJ	little
igloo-shape	JJ	igloo-shape
room	NN	room
in	IN	in
which	WDT	which
a	DT	a
group	NN	group
of	IN	of
people	NNS	person
enter	VBP	enter
and	CC	and
medicinal	JJ	medicinal
plants	NNS	plant
are	VBP	be
burned	VBN	burn
inside	IN	inside
it	PRP	it
and	CC	and
the	DT	the
place	NN	place
gets	VBZ	get
really	RB	really
warm	JJ	warm
.	.	.
</s>
<s type="decl">
A	DT	a
guide	NN	guide
asks	VBZ	ask
people	NNS	person
to	TO	to
sing	VB	sing
ancient	JJ	ancient
songs	NNS	song
to	TO	to
make	VB	make
the	DT	the
experience	NN	experience
more	RBR	more
complete	JJ	complete
.	.	.
</s>
<s type="decl">
Many	JJ	many
hotels	NNS	hotel
have	VBP	have
this	DT	this
option	NN	option
either	CC	either
in	IN	in
groups	NNS	group
or	CC	or
individual	JJ	individual
.	.	.
</s>
</p>
<p>
<s type="decl">
The	DT	the
Mexican	NNP	Mexican
Association	NNP	Association
of	IN	of
Scouts	NNPS	Scouts
runs	VBZ	run
a	DT	a
large	JJ	large
campground	NN	campground
called	VBN	call
<hi rend="italic">
Meztitla	NNP	Meztitla
</hi>
just	RB	just
outside	RB	outside
of	IN	of
town	NN	town
.	.	.
</s>
<s type="decl">
The	DT	the
camp	NN	camp
offers	VBZ	offer
warm	JJ	warm
showers	NNS	shower
,	,	,
tent	NN	tent
camping	NN	camping
,	,	,
hiking	NN	hiking
,	,	,
rock	NN	rock
climbing	NN	climbing
,	,	,
and	CC	and
rappel	NN	rappel
.	.	.
</s>
<s type="decl">
It	PRP	it
is	VBZ	be
open	JJ	open
to	IN	to
the	DT	the
public	NN	public
365	CD	365
days	NNS	day
(	-LRB-	(
except	IN	except
for	IN	for
occasional	JJ	occasional
closings	NNS	closing
due	JJ	due
to	IN	to
special	JJ	special
Scout	NNP	Scout
events	NNS	event
)	-RRB-	)
.	.	.
</s>
<s type="decl">
First-aid	JJ	First-aid
service	NN	service
is	VBZ	be
available	JJ	available
.	.	.
</s>
<s type="decl">
There	EX	there
is	VBZ	be
an	DT	a
area	NN	area
for	IN	for
campfires	NNS	campfire
.	.	.
</s>
<s type="sub">
Food	NN	food
services	NNS	service
must	MD	must
be	VB	be
arranged	VBN	arrange
in	IN	in
advance	NN	advance
.	.	.
</s>
<s type="frag">
<ref target="http://morelosturistico.com/espanol/pagina/z_252_Campamento_Meztitla.php">
Mextitla	NNP	Mextitla
(	-LRB-	(
in	IN	in
Spanish	NNP	Spanish
)	-RRB-	)
</ref>
</s>
</p>
<p>
<s type="sub">
No	DT	no
visit	NN	visit
to	IN	to
Tepoztlan	NNP	Tepoztlan
would	MD	would
be	VB	be
complete	JJ	complete
without	IN	without
climbing	VBG	climb
<hi rend="bold">
Tepozteco	NNP	Tepozteco
</hi>
to	TO	to
see	VB	see
the	DT	the
pyramid	NN	pyramid
.	.	.
</s>
</p>
<p>
<s type="decl">
The	DT	the
Dominican	JJ	Dominican
monastery	NN	monastery
and	CC	and
museum	NN	museum
is	VBZ	be
another	DT	another
must-see	NN	must-see
.	.	.
</s>
<s type="decl">
The	DT	the
building	NN	building
was	VBD	be
damaged	VBN	damage
during	IN	during
the	DT	the
<date when="2017">
2017	CD	2017
</date>
earthquake	NN	earthquake
and	CC	and
may	MD	may
be	VB	be
closed	VBN	close
at	IN	at
this	DT	this
time	NN	time
.	.	.
</s>
<s type="decl">
There	EX	there
is	VBZ	be
a	DT	a
small	JJ	small
fee	NN	fee
(	-LRB-	(
MX$	NNP	MX$
10	CD	10
)	-RRB-	)
to	TO	to
enter	VB	enter
the	DT	the
monastery/museum	NN	monastery/museum
.	.	.
</s>
<s type="decl">
The	DT	the
<hi rend="bold">
Pellicer	NNP	Pellicer
Museum	NNP	Museum
</hi>
behind	IN	behind
the	DT	the
monastery	NN	monastery
has	VBZ	have
an	DT	a
extensive	JJ	extensive
collection	NN	collection
of	IN	of
archaeological	JJ	archaeological
pieces	NNS	piece
.	.	.
</s>
</p>
<p>
<s type="decl">
The	DT	the
market	NN	market
is	VBZ	be
colorful	JJ	colorful
and	CC	and
offers	VBZ	offer
delicious	JJ	delicious
local	JJ	local
dishes	NNS	dish
.	.	.
</s>
<s type="decl">
It	PRP	it
spreads	VBZ	spread
out	RP	out
to	TO	to
cover	VB	cover
an	DT	a
entire	JJ	entire
street	NN	street
on	IN	on
Sundays	NNPS	Sunday
and	CC	and
is	VBZ	be
an	DT	a
excellent	JJ	excellent
place	NN	place
to	TO	to
buy	VB	buy
souvenirs	NNS	souvenir
.	.	.
</s>
</p>
<head>
<s type="imp">
Buy	VB	buy
</s>
</head>
<p>
<s type="decl">
There	EX	there
are	VBP	be
many	JJ	many
handicrafts	NNS	handicraft
sold	VBN	sell
in	IN	in
the	DT	the
market	NN	market
and	CC	and
nearby	JJ	nearby
shops	NNS	shop
,	,	,
as	RB	as
well	RB	well
as	IN	as
imported	VBN	import
knickknacks	NNS	knickknack
from	IN	from
around	IN	around
the	DT	the
world	NN	world
.	.	.
</s>
<s type="decl">
Mezcal	NNP	Mezcal
and	CC	and
quartz	NN	quartz
rocks	NNS	rock
are	VBP	be
produced	VBN	produce
locally	RB	locally
.	.	.
</s>
</p>
<head>
<s type="imp">
Eat	VB	eat
</s>
</head>
<list type="unordered">
<item>
<s type="decl">
<hi rend="bold">
Tepoznieves	NNP	Tepoznieve
</hi>
has	VBZ	have
multiple	JJ	multiple
locations	NNS	location
around	IN	around
town	NN	town
(	-LRB-	(
Av.	FW	av.
5	CD	5
de	NN	de
mayo	NN	mayo
,	,	,
21	CD	21
)	-RRB-	)
and	CC	and
their	PRP$	their
ice	NN	ice
cream	NN	cream
is	VBZ	be
famous	JJ	famous
.	.	.
</s>
<s type="decl">
They	PRP	they
may	MD	may
have	VB	have
up	IN	up
to	IN	to
200	CD	200
flavors	NNS	flavor
available	JJ	available
ranging	VBG	range
from	IN	from
the	DT	the
pedestrian	JJ	pedestrian
chocolate	NN	chocolate
to	IN	to
more	RBR	more
exotic	JJ	exotic
rose	NN	rise
petal	NN	petal
,	,	,
figs	NNS	fig
&amp;	CC	&amp;
mescal	NN	mescal
or	CC	or
carrot	NN	carrot
with	IN	with
chili	NN	chili
.	.	.
</s>
</item>
<item>
<s type="decl">
<hi rend="bold">
La	NNP	La
Posada	NNP	Posada
de	NNP	de
Tepoztec	NNP	Tepoztec
</hi>
is	VBZ	be
located	VBN	locate
two	CD	2
blocks	NNS	block
above	IN	above
the	DT	the
main	JJ	main
square	NN	square
.	.	.
</s>
<s type="decl">
In	IN	in
addition	NN	addition
to	IN	to
offering	VBG	offer
beautiful	JJ	beautiful
(	-LRB-	(
though	IN	though
pricey	JJ	pricey
)	-RRB-	)
lodging	NN	lodging
,	,	,
the	DT	the
restaurant	NN	restaurant
serves	VBZ	serve
delicious	JJ	delicious
local	JJ	local
cuisine	NN	cuisine
.	.	.
</s>
<s type="imp">
Sit	VB	sit
on	IN	on
the	DT	the
serene	JJ	serene
patio	NN	patio
to	TO	to
enjoy	VB	enjoy
the	DT	the
mountain	NN	mountain
and	CC	and
town	NN	town
views	NNS	view
.	.	.
</s>
<s type="decl">
Their	PRP$	their
Chicken	NN	chicken
Mole	NNP	Mole
is	VBZ	be
delicious	JJ	delicious
.	.	.
</s>
</item>
<item>
<s type="decl">
<hi rend="bold">
Cuatecomate	NNP	Cuatecomate
</hi>
is	VBZ	be
a	DT	a
prehispanic	JJ	prehispanic
restaurant	NN	restaurant
.	.	.
</s>
<s type="decl">
It	PRP	it
is	VBZ	be
located	VBN	locate
on	IN	on
Av	NNP	Av
Revolucion	NNP	Revolucion
#10	NNP	#10
,	,	,
interior	NN	interior
of	IN	of
Plaza	NNP	Plaza
las	NNP	las
Flores	NNP	Flores
.	.	.
</s>
</item>
<item>
<s type="decl">
<hi rend="bold">
El	NNP	El
Ciruelo	NNP	Ciruelo
</hi>
at	IN	at
Zaragoza	NNP	Zaragoza
#10	NNP	#10
is	VBZ	be
a	DT	a
moderately-priced	JJ	moderately-priced
restaurant	NN	restaurant
that	WDT	that
features	VBZ	feature
local	JJ	local
food	NN	food
.	.	.
</s>
<s type="decl">
It	PRP	it
is	VBZ	be
apt	JJ	apt
for	IN	for
vegetarians	NNS	vegetarian
and	CC	and
vegans	NNS	vegan
.	.	.
</s>
<s type="frag">
Tel	NNP	Tel
.	.	.
<date when="1203">
52-739-395-1203.	CD	52-739-395-1203.
</date>
</s>
</item>
<item>
<s type="decl">
<hi rend="bold">
La	NNP	La
Sombra	NNP	Sombra
del	NNP	del
Sabino	NNP	Sabino
</hi>
is	VBZ	be
a	DT	a
moderately-priced	JJ	moderately-priced
cafe	NN	cafe
near	IN	near
the	DT	the
toll	NN	toll
booth	NN	booth
at	IN	at
Revolucion	NNP	Revolucion
#45	NNP	#45
,	,	,
Barrio	NNP	Barrio
San	NNP	San
Jose	NNP	Jose
.	.	.
</s>
<s type="frag">
Tel	NNP	Tel
.	.	.
52-739-395=0369.	CD	52-739-395=0369.
</s>
<s type="decl">
It	PRP	it
offers	VBZ	offer
Mexican	JJ	Mexican
food	NN	food
for	IN	for
breakfast	NN	breakfast
or	CC	or
afternoon	NN	afternoon
dinner	NN	dinner
.	.	.
</s>
</item>
<item>
<s type="decl">
Many	JJ	many
visitors	NNS	visitor
choose	VBP	choose
to	TO	to
eat	VB	eat
tacos	NNS	taco
,	,	,
gorditas	NNS	gordita
,	,	,
and	CC	and
quesadillas	NNS	quesadilla
in	IN	in
the	DT	the
market	NN	market
.	.	.
</s>
<s type="decl">
<hi rend="italic">
Flor	NNP	Flor
de	NNP	de
calabaza	NNP	Calabaza
</hi>
is	VBZ	be
quite	RB	quite
popular	JJ	popular
.	.	.
</s>
<s type="decl">
Dried	VBN	dry
grasshoppers	NNS	grasshoppper
(	-LRB-	(
<hi rend="italic">
chapulines	NNS	chapuline
</hi>
)	-RRB-	)
are	VBP	be
also	RB	also
popular	JJ	popular
.	.	.
</s>
</item>
</list>
<head>
<s type="imp">
Drink	VB	drink
</s>
</head>
<p>
<s type="decl">
<hi rend="italic">
Tepoztēcatl	NNP	Tepoztēcatl
</hi>
was	VBD	be
the	DT	the
god	NN	god
who	WP	who
invented	VBD	invent
pulque	NN	pulque
in	IN	in
Tepoztlan	NNP	Tepoztlan
.	.	.
</s>
</p>
<list type="unordered">
<item>
<s type="frag">
<hi rend="bold">
Pulques	NNP	Pulque
El	NNP	El
Nectar	NNP	Nectar
Tepozteco	NNP	Tepozteco
</hi>
,	,	,
62520	CD	62520
,	,	,
Revolución	NNP	Revolución
de	NNP	de
<date when="1910">
1910	CD	1910
</date>
36	CD	36
,	,	,
San	NNP	San
Miguel	NNP	Miguel
,	,	,
Tepoztlán	NNP	Tepoztlán
,	,	,
☏	SYM	☏
+527393950212	CD	+527393950212
.	.	.
</s>
<s type="frag">
Fri	NNP	Friday
,	,	,
Sat	NNP	Saturday
,	,	,
Sun	NNP	Sun
<time when="1000">
10AM	CD	10AM
</time>
to	IN	to
<time when="2000">
8	CD	8
PM	NN	PM
</time>
.	.	.
</s>
<s type="decl">
pulqueria	NNP	pulqueria
MX$	NNP	MX$
20	CD	20
for	IN	for
200	CD	200
mL	NNS	millileter
.	.	.
</s>
</item>
<item>
<s type="frag">
<hi rend="bold">
Pulques	NNP	Pulque
El	NNP	El
Rey	NNP	Rey
Tepozteco	NNP	Tepozteco
</hi>
,	,	,
Santisima	NNP	Santisima
Trinidad	NNP	Trinidad
,	,	,
62520	CD	62520
Tepoztlán	NNP	Tepoztlán
.	.	.
</s>
<s type="frag">
pulqueria	NNP	pulqueria
</s>
</item>
<item>
<s type="frag">
<hi rend="bold">
Lagartija	NNP	Lagartija
Club	NNP	Club
Mezcal	NNP	Mezcal
</hi>
,	,	,
Isabel	NNP	Isabel
La	NNP	La
Católica	NNP	Católica
12	CD	12
,	,	,
San	NNP	San
Miguel	NNP	Miguel
,	,	,
62520	CD	62520
Tepoztlán	NNP	Tepoztlán
,	,	,
☏	SYM	☏
+527393950196	CD	+527393950196
.	.	.
</s>
<s type="frag">
Daily	JJ	Daily
12:30	CD	12:30
-	SYM	-
19:30	CD	19:30
(	-LRB-	(
Fri	NNP	Friday
,	,	,
Sat	NNP	Saturday
to	IN	to
20:00	CD	20:00
)	-RRB-	)
.	.	.
</s>
<s type="frag">
mezcal	NN	mezcal
bar	NN	bar
</s>
</item>
<item>
<s type="frag">
<hi rend="bold">
Mezcalería	NNP	Mezcalería
La	NNP	La
Cueva	NNP	Cueva
</hi>
,	,	,
Av.	NNP	Av.
Revolución	NNP	Revolución
2	CD	2
,	,	,
Santo	NNP	Santo
Domingo	NNP	Domingo
,	,	,
62520	CD	62520
Tepoztlán	NNP	Tepoztlán
.	.	.
</s>
<s type="frag">
Fri	NNP	Friday
noon	NN	noon
to	IN	to
midnight	NN	midnight
,	,	,
Sat	NNP	Saturday
noon	NN	noon
to	IN	to
<time when="0200">
2AM	NN	2AM
</time>
,	,	,
Sun	NNP	Sun
noon	NN	noon
to	IN	to
<time when="2300">
11	CD	11
PM	NN	PM
</time>
.	.	.
</s>
<s type="frag">
mezcal	JJ	mezcal
bar	NN	bar
with	IN	with
live	JJ	live
music	NN	music
</s>
</item>
</list>
<head>
<s type="frag">
Sleep	NN	sleep
</s>
</head>
<p>
<s type="decl">
Sleeping	VBG	sleep
in	IN	in
Tepoztlan	NNP	Tepoztlan
can	MD	can
be	VB	be
noisy	JJ	noisy
at	IN	at
times	NNS	time
(	-LRB-	(
in	IN	in
<date when="2010-12">
December	NNP	December
2010	CD	2010
</date>
,	,	,
the	DT	the
church	NN	church
bells	NNS	bell
seemed	VBD	seem
to	TO	to
ring	VB	ring
on	IN	on
the	DT	the
half	JJ	half
hour	NN	hour
all	DT	all
night	NN	night
)	-RRB-	)
.	.	.
</s>
</p>
<p>
<s type="decl">
There	EX	there
are	VBP	be
two	CD	2
campgrounds	NNS	campground
nearby	RB	nearby
:	:	:
<hi rend="bold">
Camhomila	NNP	Camhomila
</hi>
(	-LRB-	(
YMCA	NNP	YMCA
camp	NN	camp
;	:	;
accepts	VBZ	accept
trailers	NNS	trailer
and	CC	and
has	VBZ	have
cabins	NNS	cabin
)	-RRB-	)
and	CC	and
<hi rend="bold">
Meztitla	NNP	Meztitla
</hi>
(	-LRB-	(
Scouts	NNP	Scouts
of	IN	of
Mexico	NNP	Mexico
,	,	,
tents	NNS	tent
only	RB	only
;	:	;
hiking	NN	hiking
,	,	,
rock	NN	rock
climbing	NN	climbing
,	,	,
rappel	NN	rappel
.	.	.
)	-RRB-	)
</s>
<s type="other">
Both	DT	both
nice	JJ	nice
,	,	,
safe	JJ	safe
,	,	,
and	CC	and
open	JJ	open
to	IN	to
the	DT	the
public	NN	public
.	.	.
</s>
</p>
<p>
<s type="decl">
<hi rend="bold">
Posada	NNP	Posada
Ali	NNP	Ali
</hi>
is	VBZ	be
nice	JJ	nice
place	NN	place
with	IN	with
a	DT	a
good	JJ	good
view	NN	view
of	IN	of
the	DT	the
cliffs	NNS	cliff
.	.	.
</s>
<s type="decl">
It	PRP	it
costs	VBZ	cost
around	RB	around
M$	NNP	M$
500	CD	500
on	IN	on
weekdays	NNS	weekday
(	-LRB-	(
prices	NNS	price
seem	VBP	seem
to	TO	to
vary	VB	vary
)	-RRB-	)
.	.	.
</s>
</p>
<list type="unordered">
<item>
<s type="frag">
<hi rend="bold">
Amomoxtli	NNP	Amomoxtli
</hi>
,	,	,
Calle	NNP	Calle
Netzahualcóyotl	NNP	Netzahualcóyotl
115	CD	115
,	,	,
Valle	NNP	Valle
de	NNP	de
Atongo	NNP	Atongo
,	,	,
62520	CD	62520
Tepoztlán	NNP	Tepoztlán
(	-LRB-	(
4	CD	4
m	NN	meter
from	IN	from
tollway	NN	tollway
,	,	,
3	CD	3
km	NN	kilometer
from	IN	from
ruins	NNS	ruin
)	-RRB-	)
,	,	,
☏	SYM	☏
+527393950012	CD	+527393950012
.	.	.
</s>
<s type="frag">
Check-in	NN	check-in
:	:	:
<time when="1500">
3PM	CD	3PM
</time>
,	,	,
check-out	NN	check-out
:	:	:
12	CD	12
noon	NN	noon
.	.	.
</s>
<s type="frag">
large	JJ	large
gardens	NNS	garden
,	,	,
suites	NNS	suite
,	,	,
cabins	NNS	cabin
,	,	,
bar	NN	bar
,	,	,
swimming	NN	swimming
pool	NN	pool
,	,	,
wi-fi	NN	wi-fi
,	,	,
spa	NN	spa
MX$	NN	MX$
3,924	CD	38924
.	.	.
</s>
</item>
<item>
<hi rend="bold">
<s type="frag">
Hotel	NNP	Hotel
Boutique	NNP	Boutique
</s>
<s type="frag">
Casa	NNP	Casa
Fernanda	NNP	Fernanda
</s>
</hi>
<s type="frag">
,	,	,
De	NNP	De
Niño	NNP	Niño
Artillero	NNP	Artillero
20	CD	20
,	,	,
San	NNP	San
Jose	NNP	Jose
,	,	,
62520	CD	62520
Tepoztlán	NNP	Tepoztlán
,	,	,
☏	SYM	☏
+527393950522	CD	+527393950522
.	.	.
</s>
<s type="frag">
Check-in	NN	check-in
:	:	:
<time when="1500">
3	CD	3
PM	NN	PM
</time>
,	,	,
check-out	NN	check-out
:	:	:
<time when="1300">
1	CD	1
PM	NN	PM
</time>
.	.	.
</s>
<s type="frag">
couples	NNS	couple
,	,	,
wi-fi	NN	wi-fi
,	,	,
air	NN	air
conditioning	NN	conditioning
,	,	,
cable	NN	cable
TV	NN	TV
,	,	,
spa	NN	spa
,	,	,
swimming	NN	swimming
pool	NN	pool
,	,	,
three	CD	3
gardens	NNS	garden
,	,	,
view	NN	view
of	IN	of
mountains	NNS	mountain
MX$	NNP	MX$
2,898	CD	2889
.	.	.
</s>
</item>
<item>
<s type="frag">
<hi rend="bold">
Hostal	NNP	Hostal
de	NNP	de
la	NNP	la
Luz	NNP	Luz
Spa	NNP	Spa
Holistic	NNP	Holistic
Resort	NNP	Resort
</hi>
,	,	,
Carretera	NNP	Carretera
Federal	NNP	Federal
Tepoztlan	NNP	Tepoztlan
</s>
<s type="frag">
Amatlan	NNP	Amatlan
s/n	NNP	S/n
Km4	NNP	Km4
,	,	,
☏	SYM	☏
+527393953374	CD	+527393953374
.	.	.
</s>
<s type="decl">
Hostal	NNP	Hostal
de	NNP	de
la	NNP	la
Luz	NNP	Luz
Spa	NNP	Spa
Holistic	NNP	Holistic
Resort	NNP	Resort
provides	VBZ	provide
suites	NNS	suite
2	CD	2
twin	NN	twin
beds	NNS	bed
,	,	,
junior	JJ	junior
suite	NN	suite
queen	NN	queen
bed	NN	bed
,	,	,
junior	JJ	junior
suite	NN	suite
</s>
<s type="frag">
nicho	NNP	Nicho
2	CD	2
double	JJ	double
beds	NNS	bed
,	,	,
junior	NN	junior
suite	NN	suite
balcony	NN	balcony
king	NN	king
bed	NN	bed
,	,	,
master	NN	master
suite	NN	suite
king	NN	king
bed	NN	bed
,	,	,
master	NN	master
suite	NN	suite
2	CD	2
double	JJ	double
beds	NNS	bed
and	CC	and
gran	NN	gran
master	NN	master
suite	NN	suite
with	IN	with
complimentary	JJ	complimentary
buffet	NN	buffet
breakfast	NN	breakfast
,	,	,
private	JJ	private
bathroom	NN	bathroom
and	CC	and
telephone	NN	telephone
.	.	.
</s>
<s type="decl">
Its	PRP$	its
facilities	NNS	facility
and	CC	and
services	NNS	service
include	VBP	include
swimming	NN	swimming
pool	NN	pool
,	,	,
Shambhala	NNP	Shambhala
restaurant	NN	restaurant
,	,	,
Sirio	NNP	Sirio
Holistic	NNP	Holistic
Spa	NNP	Spa
and	CC	and
Feng	NNP	Feng
Shui	NNP	Shui
bioenergetic	JJ	bioenergetic
design	NN	design
.	.	.
</s>
</item>
<item>
<s type="frag">
<hi rend="bold">
Hospedaje	NNP	Hospedaje
San	NNP	San
Antonio	NNP	Antonio
</hi>
,	,	,
Calle	NNP	Calle
Netzahualcóyotl	NNP	Netzahualcóyotl
5	CD	5
,	,	,
Santisima	NNP	Santisima
Trinidad	NNP	Trinidad
,	,	,
62520	CD	62520
Tepoztlán	NNP	Tepoztlán
,	,	,
Mor	NNP	Mor
,	,	,
☏	SYM	☏
+527393957478	CD	+527393957478
.	.	.
</s>
<s type="frag">
Good	JJ	good
location	NN	location
,	,	,
swimming	NN	swimming
pool	NN	pool
mx$	RB	mx$
898	CD	898
.	.	.
</s>
</item>
</list>
</text>