<?xml version='1.0' encoding='utf8'?>
<text id="AMALGUM_news_wreckage" title="Iran: Wreckage found of plane crashed in mountains; all believed dead" shortTitle="wreckage" type="news" dateCollected="2019-11-05" dateCreated="2018-02-19" dateModified="2018-12-31" sourceURL="https://en.wikinews.org/wiki/Iran%3A_Wreckage_found_of_plane_crashed_in_mountains%3B_all_believed_dead" speakerList="none" speakerCount="0">
<head>
<s type="frag">
Iran	NNP	Iran
:	:	:
Wreckage	NN	wreckage
found	VBN	find
of	IN	of
plane	NN	plane
crashed	VBD	crash
in	IN	in
mountains	NNS	mountain
;	:	;
all	DT	all
believed	VBN	believe
dead	JJ	dead
</s>
</head>
<p>
<s type="frag">
<hi rend="bold">
Wednesday	NNP	Wednesday
,	,	,
<date when="2018-02-21">
February	NNP	February
21	CD	21
,	,	,
2018	CD	2018
</date>
</hi>
</s>
</p>
<figure>
<caption>
<s type="frag">
Aseman	NNP	Aseman
Airlines	NNP	Airline
ATR	NNP	ATR
72	CD	72
,	,	,
from	IN	from
file	NN	file
.	.	.
</s>
<s type="frag">
Image	NN	image
:	:	:
<ref target="http://www.aeroprints.com/">
Aeroprints.com	NNP	Aeroprints.com
</ref>
.	.	.
</s>
<s type="frag">
(	-LRB-	(
<ref target="https://en.wikinews.org/wiki/File:EP-ATS_ATR.72_Iran_Aseman_Airlines_(7691719536).jpg">
Reuseterms	NNPS	Reuseterm
</ref>
.	.	.
)	-RRB-	)
</s>
</caption>
</figure>
<p>
<s type="decl">
Yesterday	NN	yesterday
,	,	,
the	DT	the
<ref target="https://en.wikinews.org/wiki/Iran">
Iranian	JJ	Iranian
</ref>
military	NN	military
announced	VBD	announce
the	DT	the
wreckage	NN	wreckage
of	IN	of
an	DT	a
<ref target="https://en.wikinews.org/wiki/Iran_Aseman_Airlines">
Aseman	NNP	Aseman
Airlines	NNP	Airline
</ref>
airplane	NN	airplane
,	,	,
which	WDT	which
went	VBD	go
missing	JJ	miss
on	IN	on
<date when="2018-02-18">
Sunday	NNP	Sunday
morning	NN	morning
</date>
shortly	RB	shortly
before	IN	before
it	PRP	it
was	VBD	be
due	JJ	due
to	TO	to
land	NN	land
in	IN	in
<ref target="https://en.wikipedia.org/wiki/Yasuj">
Yasuj	NNP	Yasuj
</ref>
,	,	,
had	VBD	have
been	VBN	be
located	VBN	locate
at	IN	at
an	DT	a
elevation	NN	elevation
of	IN	of
about	RB	about
13,000feet	CD	13,000feet
(	-LRB-	(
4,000m	CD	40000
)	-RRB-	)
in	IN	in
the	DT	the
<ref target="https://en.wikipedia.org/wiki/Zagros%20Mountains">
Zagros	NNP	Zagros
Mountains	NNPS	Mountain
</ref>
.	.	.
</s>
<s type="decl">
All	DT	all
65	CD	65
people	NNS	person
on	IN	on
board	NN	board
were	VBD	be
presumed	VBN	presume
dead	JJ	dead
.	.	.
</s>
<s type="decl">
Crews	NNS	crew
were	VBD	be
searching	VBG	search
for	IN	for
the	DT	the
aircraft	NN	aircraft
's	POS	's
two	CD	2
<ref target="https://en.wikipedia.org/wiki/Flight%20recorder">
black	JJ	black
boxes	NNS	box
</ref>
to	TO	to
try	VB	try
to	TO	to
determine	VB	determine
why	WRB	why
it	PRP	it
crashed	VBD	crash
.	.	.
</s>
</p>
<p>
<s type="decl">
Ramezan	NNP	Ramezan
Sharif	NNP	Sharif
,	,	,
a	DT	a
spokesman	NN	spokesman
for	IN	for
Iran	NNP	Iran
's	POS	's
<ref target="https://en.wikipedia.org/wiki/Islamic%20Revolutionary%20Guard%20Corps">
Revolutionary	NNP	Revolutionary
Guards	NNPS	Guards
</ref>
,	,	,
said	VBD	say
wreckage	NN	wreckage
of	IN	of
the	DT	the
<ref target="https://en.wikipedia.org/wiki/ATR%2072">
ATR	NNP	ATR
72-500	CD	72-500
</ref>
twin-engine	NN	twin-engine
<ref target="https://en.wikipedia.org/wiki/turboprop">
turboprop	NN	turboprop
</ref>
had	VBD	have
been	VBN	be
sighted	VBN	sight
by	IN	by
a	DT	a
military	JJ	military
<ref target="https://en.wikipedia.org/wiki/Unmanned%20aerial%20vehicle">
drone	NN	drone
</ref>
and	CC	and
helicopters	NNS	helicopter
had	VBD	have
then	RB	then
been	VBN	be
sent	VBN	send
to	IN	to
the	DT	the
location	NN	location
.	.	.
</s>
<s type="decl">
Helicopter	NNP	Helicopter
pilot	NN	pilot
Captain	NNP	Captain
Soheili	NNP	Soheili
said	VBD	say
on	IN	on
state	NN	state
television	NN	television
the	DT	the
wreckage	NN	wreckage
was	VBD	be
only	RB	only
some	RB	some
100feet	CD	100feet
(	-LRB-	(
30m	CD	30m
)	-RRB-	)
from	IN	from
a	DT	a
peak	NN	peak
on	IN	on
<ref target="https://en.wikipedia.org/wiki/Mount%20Dena">
Mount	NNP	Mount
Dena	NNP	Dena
</ref>
,	,	,
and	CC	and
"	``	''
large	JJ	large
parts	NNS	part
of	IN	of
the	DT	the
plane	NN	plane
,	,	,
which	WDT	which
were	VBD	be
labeled	VBN	label
with	IN	with
the	DT	the
Aseman	NNP	Aseman
company	NN	company
logo	NN	logo
"	''	''
were	VBD	be
visible	JJ	visible
.	.	.
</s>
<s type="decl">
The	DT	the
Revolutionary	NNP	Revolutionary
Guards	NNPS	Guards
released	VBD	release
photos	NNS	photo
in	IN	in
which	WDT	which
they	PRP	they
said	VBD	say
bodies	NNS	body
of	IN	of
victims	NNS	victim
could	MD	could
be	VB	be
seen	VBN	see
.	.	.
</s>
<s type="decl">
Regional	JJ	Regional
medical	JJ	medical
center	NN	center
director	NN	director
Ghafoor	NNP	Ghafoor
Rastinrooz	NNP	Rastinrooz
told	VBD	tell
the	DT	the
official	JJ	official
<ref target="https://en.wikipedia.org/wiki/Islamic%20Republic%20News%20Agency">
IRNA	NNP	IRNA
</ref>
news	NN	news
agency	NN	agency
that	IN	that
helicopters	NNS	helicopter
were	VBD	be
unable	JJ	unable
to	TO	to
land	VB	land
at	IN	at
the	DT	the
site	NN	site
because	IN	because
of	IN	of
"	``	''
deep	JJ	deep
and	CC	and
dangerous	JJ	dangerous
crevices	NNS	crevice
in	IN	in
the	DT	the
area	NN	area
of	IN	of
the	DT	the
crash	NN	crash
"	''	''
.	.	.
</s>
<s type="decl">
General	NNP	General
Kiumars	NNP	Kiumars
Heidari	NNP	Heidari
,	,	,
chief	NN	chief
of	IN	of
ground	NN	ground
forces	NNS	force
in	IN	in
the	DT	the
<ref target="https://en.wikipedia.org/wiki/Islamic%20Republic%20of%20Iran%20Army">
Iranian	NNP	Iranian
Army	NNP	Army
</ref>
,	,	,
told	VBD	tell
the	DT	the
<ref target="https://en.wikipedia.org/wiki/Fars%20News%20Agency">
Fars	NNP	Far
News	NNP	News
Agency	NNP	Agency
</ref>
the	DT	the
dead	JJ	dead
would	MD	would
have	VB	have
to	TO	to
be	VB	be
brought	VBN	bring
down	IN	down
the	DT	the
mountain	NN	mountain
by	IN	by
commandos	NNS	commando
using	VBG	use
specialized	JJ	specialized
ground	NN	ground
vehicles	NNS	vehicle
.	.	.
</s>
</p>
<p>
<s type="decl">
The	DT	the
plane	NN	plane
took	VBD	take
off	RP	off
at	IN	at
about	RB	about
0430UTC	CD	0430UTC
on	IN	on
<date when="2018-02-18">
Sunday	NNP	Sunday
</date>
from	IN	from
the	DT	the
<ref target="https://en.wikinews.org/wiki/Iran">
Iranian	JJ	Iranian
</ref>
capital	NN	capital
,	,	,
<ref target="https://en.wikinews.org/wiki/Tehran">
Tehran	NNP	Tehran
</ref>
,	,	,
on	IN	on
Aseman	NNP	Aseman
Airlines	NNP	Airline
route	NN	route
EP3704	NNP	EP3704
to	IN	to
Yasuj	NNP	Yasuj
,	,	,
in	IN	in
the	DT	the
southwest	NN	southwest
of	IN	of
the	DT	the
country	NN	country
.	.	.
</s>
<s type="decl">
It	PRP	it
vanished	VBD	vanish
from	IN	from
controllers	NNS	controller
'	POS	's
radar	NN	radar
screens	NNS	screen
at	IN	at
about	RB	about
8:52	CD	8:52
<ref target="https://en.wikipedia.org/wiki/Iran%20Time">
local	JJ	local
time	NN	time
</ref>
,	,	,
0522UTC	CD	0522UTC
,	,	,
and	CC	and
there	EX	there
were	VBD	be
reports	NNS	report
from	IN	from
people	NNS	person
in	IN	in
the	DT	the
area	NN	area
of	IN	of
Samirom	NNP	Samirom
,	,	,
about	RB	about
14miles	NNS	14mile
(	-LRB-	(
22km	CD	22km
)	-RRB-	)
from	IN	from
its	PRP$	its
destination	NN	destination
in	IN	in
<ref target="https://en.wikipedia.org/wiki/Isfahan%20Province">
Isfahan	NNP	Isfahan
Province	NNP	Province
</ref>
,	,	,
of	IN	of
seeing	VBG	see
it	PRP	it
attempting	VBG	attempt
an	DT	a
emergency	NN	emergency
landing	NN	landing
in	IN	in
a	DT	a
pasture	NN	pasture
and	CC	and
of	IN	of
hearing	VBG	hear
the	DT	the
crash	NN	crash
.	.	.
</s>
<s type="decl">
Hundreds	NNS	hundred
of	IN	of
searchers	NNS	searcher
organized	VBN	organize
by	IN	by
the	DT	the
<ref target="https://en.wikinews.org/wiki/Red_Crescent">
Red	NNP	Red
Crescent	NNP	Crescent
</ref>
and	CC	and
using	VBG	use
drones	NNS	drone
and	CC	and
dogs	NNS	dog
combed	VBD	comb
the	DT	the
mountainous	JJ	mountainous
terrain	NN	terrain
but	CC	but
were	VBD	be
hampered	VBN	hamper
by	IN	by
windy	JJ	windy
,	,	,
foggy	JJ	foggy
conditions	NNS	condition
and	CC	and
heavy	JJ	heavy
snow	NN	snow
.	.	.
</s>
<s type="decl">
The	DT	the
search	NN	search
had	VBD	have
to	TO	to
be	VB	be
suspended	VBN	suspend
on	IN	on
<date when="2018-02-18">
Sunday	NNP	Sunday
</date>
.	.	.
</s>
<s type="decl">
It	PRP	it
resumed	VBD	resume
at	IN	at
dawn	NN	dawn
on	IN	on
<date when="2018-02-19">
Monday	NNP	Monday
</date>
but	CC	but
weather	NN	weather
then	RB	then
forced	VBD	force
grounding	VBG	ground
the	DT	the
helicopters	NNS	helicopter
.	.	.
</s>
<s type="decl">
At	IN	at
one	CD	one
point	NN	point
on	IN	on
<date when="2018-02-19">
Monday	NNP	Monday
</date>
local	JJ	local
officials	NNS	official
announced	VBD	announce
searchers	NNS	searcher
had	VBD	have
found	VBN	find
the	DT	the
wreckage	NN	wreckage
,	,	,
only	RB	only
to	TO	to
have	VB	have
the	DT	the
national	JJ	national
civil	JJ	civil
aviation	NN	aviation
agency	NN	agency
and	CC	and
the	DT	the
Red	NNP	Red
Crescent	NNP	Crescent
indicate	VBP	indicate
the	DT	the
statement	NN	statement
had	VBD	have
been	VBN	be
premature	JJ	premature
.	.	.
</s>
<s type="decl">
A	DT	a
demonstration	NN	demonstration
was	VBD	be
reported	VBN	report
by	IN	by
more	RBR	more
than	IN	than
100people	NN	100people
outside	IN	outside
a	DT	a
Dena	NNP	Dena
Kooh	NNP	Kooh
government	NN	government
office	NN	office
,	,	,
demanding	VBG	demand
resignations	NNS	resignation
.	.	.
</s>
</p>
<p>
<s type="decl">
The	DT	the
plane	NN	plane
reportedly	RB	reportedly
had	VBD	have
a	DT	a
crew	NN	crew
of	IN	of
six	CD	6
—	:	—
a	DT	a
pilot	NN	pilot
and	CC	and
a	DT	a
co-pilot	NN	co-pilot
,	,	,
two	CD	2
flight	NN	flight
attendants	NNS	attendant
,	,	,
and	CC	and
two	CD	2
security	NN	security
guards	NNS	guard
—	:	—
and	CC	and
59	CD	59
passengers	NNS	passenger
,	,	,
one	CD	one
of	IN	of
them	PRP	they
a	DT	a
child	NN	child
.	.	.
</s>
<s type="decl">
A	DT	a
man	NN	man
who	WP	who
recounted	VBD	recount
missing	VBG	miss
the	DT	the
flight	NN	flight
told	VBD	tell
the	DT	the
<ref target="https://en.wikipedia.org/wiki/Tabnak">
Tabnak	NNP	Tabnak
</ref>
news	NN	news
site	NN	site
"	``	''
God	NNP	God
has	VBZ	have
been	VBN	be
really	RB	really
kind	JJ	kind
to	IN	to
me	PRP	I
"	''	''
,	,	,
expressing	VBG	express
his	PRP$	his
sadness	NN	sadness
over	IN	over
those	DT	this
who	WP	who
had	VBD	have
died	VBN	die
.	.	.
</s>
</p>
<p>
<s type="decl">
The	DT	the
aircraft	NN	aircraft
was	VBD	be
24	CD	24
years	NNS	year
old	JJ	old
.	.	.
</s>
<s type="decl">
Aseman	NNP	Aseman
Airlines	NNPS	Airline
,	,	,
Iran	NNP	Iran
's	POS	's
third	RB	third
largest	JJS	large
air	NN	air
carrier	NN	carrier
and	CC	and
owned	VBN	own
by	IN	by
the	DT	the
national	JJ	national
civil	JJ	civil
service	NN	service
pension	NN	pension
foundation	NN	foundation
,	,	,
said	VBD	say
it	PRP	it
had	VBD	have
been	VBN	be
in	IN	in
storage	NN	storage
for	IN	for
seven	CD	7
years	NNS	year
before	IN	before
recently	RB	recently
being	VBG	be
placed	VBN	place
in	IN	in
operation	NN	operation
again	RB	again
.	.	.
</s>
<s type="decl">
Iran	NNP	Iran
's	POS	's
aircraft	NN	aircraft
are	VBP	be
aging	VBG	age
and	CC	and
the	DT	the
country	NN	country
has	VBZ	have
been	VBN	be
prevented	VBN	prevent
from	IN	from
buying	VBG	buy
spare	NN	spare
parts	NNS	part
by	IN	by
international	JJ	international
sanctions	NNS	sanction
imposed	VBN	impose
in	IN	in
response	NN	response
to	IN	to
its	PRP$	its
<ref target="https://en.wikipedia.org/wiki/Nuclear%20program%20of%20Iran">
nuclear	JJ	nuclear
program	NN	program
</ref>
.	.	.
</s>
<s type="decl">
Those	DT	this
sanctions	NNS	sanction
were	VBD	be
to	TO	to
be	VB	be
lifted	VBN	lift
under	IN	under
an	DT	a
<ref target="https://en.wikipedia.org/wiki/Joint%20Comprehensive%20Plan%20of%20Action">
agreement	NN	agreement
from	IN	from
<date when="2015">
2015	CD	2015
</date>
</ref>
,	,	,
and	CC	and
Iranian	JJ	Iranian
airlines	NNS	airline
,	,	,
including	VBG	include
Aseman	NNP	Aseman
,	,	,
have	VBP	have
ordered	VBN	order
new	JJ	new
planes	NNS	plane
from	IN	from
both	CC	both
<ref target="https://en.wikinews.org/wiki/Airbus">
Airbus	NNP	Airbus
</ref>
and	CC	and
<ref target="https://en.wikinews.org/wiki/Boeing">
Boeing	NNP	Boeing
</ref>
.	.	.
</s>
<s type="decl">
However	RB	however
,	,	,
since	IN	since
becoming	VBG	become
US	NNP	US
President	NNP	President
,	,	,
<ref target="https://en.wikinews.org/wiki/Donald_Trump">
Donald	NNP	Donald
Trump	NNP	Trump
</ref>
has	VBZ	have
declined	VBN	decline
to	TO	to
recertify	VB	recertify
the	DT	the
agreement	NN	agreement
.	.	.
</s>
</p>
<p>
<s type="decl">
There	EX	there
have	VBP	have
been	VBN	be
a	DT	a
number	NN	number
of	IN	of
serious	JJ	serious
Iranian	JJ	Iranian
air	NN	air
accidents	NNS	accident
in	IN	in
modern	JJ	modern
times	NNS	time
.	.	.
</s>
<s type="decl">
In	IN	in
<date when="2011">
2011	CD	2011
</date>
,	,	,
at	IN	at
least	JJS	least
77	CD	77
people	NNS	person
died	VBD	die
when	WRB	when
an	DT	a
<ref target="https://en.wikipedia.org/wiki/Iran%20Air">
Iran	NNP	Iran
Air	NNP	Air
</ref>
<ref target="https://en.wikipedia.org/wiki/Boeing%20727">
Boeing	NNP	Boeing
727	CD	727
</ref>
crashed	VBD	crash
during	IN	during
an	DT	a
emergency	NN	emergency
landing	NN	landing
.	.	.
</s>
</p>
<p>
<s type="decl">
The	DT	the
pilot	NN	pilot
in	IN	in
the	DT	the
current	JJ	current
crash	NN	crash
,	,	,
Captain	NNP	Captain
Hojjatallah	NNP	Hojjatallah
Foulad	NNP	Foulad
,	,	,
successfully	RB	successfully
landed	VBD	land
an	DT	a
ATR	NNP	ATR
72	CD	72
at	IN	at
the	DT	the
airport	NN	airport
in	IN	in
Yasuj	NNP	Yasuj
in	IN	in
<date when="2013">
2013	CD	2013
</date>
after	IN	after
one	CD	one
of	IN	of
the	DT	the
engines	NNS	engine
failed	VBD	fail
.	.	.
</s>
</p>
</text>